[{
  "_id": {
    "$oid": "6894a1a960c27baf53ab4c91"
  },
  "Aname": {
    "Name": "GIFT",
    "Mname": "CHIKODI",
    "Surname": "ABIANURU"
  },
  "State": "",
  "LocalGovernment": "",
  "Sex": "",
  "Bloodgroup": "",
  "PhoneNumber": "",
  "EmergencyNo": "",
  "RegNo": "M25/002",
  "Validity": "",
  "picturepath": "image/63052.jpg",
  "imgurl": "https://drive.google.com/file/d/1SAscCORWyyxxpIB38US6L8_BTR9-m05h/view?usp=drivesdk",
  "image": "https://lh3.googleusercontent.com/d/1SAscCORWyyxxpIB38US6L8_BTR9-m05h=s400?authuser=0",
  "time": "2025-08-07 12:52:57",
  "field": "070de292-5579-4055-98b0-23378f6c9f43",
  "id": 386,
  "__v": 0
},
{
  "_id": {
    "$oid": "6894a23c60c27baf53ab4c9a"
  },
  "Aname": {
    "Name": "PRECIOUS",
    "Mname": "OLUOMACHI",
    "Surname": "UZODINMA"
  },
  "State": "",
  "LocalGovernment": "",
  "Sex": "",
  "Bloodgroup": "",
  "PhoneNumber": "",
  "EmergencyNo": "",
  "RegNo": "M25/096",
  "Validity": "2025_2027",
  "picturepath": "image/83155.jpg",
  "imgurl": "https://drive.google.com/file/d/1E1La5qnr2gQdVO5zeO8XxkkKXPJ1h5eV/view?usp=drivesdk",
  "image": "https://lh3.googleusercontent.com/d/1E1La5qnr2gQdVO5zeO8XxkkKXPJ1h5eV=s400?authuser=0",
  "time": "2025-08-07 12:55:24",
  "field": "bbaa9c07-6963-43a1-9556-8832253f3e49",
  "id": 387,
  "__v": 0
},
{
  "_id": {
    "$oid": "6894a34b60c27baf53ab4ca3"
  },
  "Aname": {
    "Name": "JOSEPH",
    "Mname": "",
    "Surname": "ONUOHA"
  },
  "State": "",
  "LocalGovernment": "",
  "Sex": "",
  "Bloodgroup": "",
  "PhoneNumber": "",
  "EmergencyNo": "",
  "RegNo": "M25/079",
  "Validity": "2025-2027",
  "picturepath": "image/81324.jpg",
  "imgurl": "https://drive.google.com/file/d/1fpJcW_lfT6DTZu5s_SjGxL4BlPAb04qV/view?usp=drivesdk",
  "image": "https://lh3.googleusercontent.com/d/1fpJcW_lfT6DTZu5s_SjGxL4BlPAb04qV=s400?authuser=0",
  "time": "2025-08-07 12:59:55",
  "field": "3505e966-232b-478e-89aa-14bef4a51d15",
  "id": 388,
  "__v": 0
},
{
  "_id": {
    "$oid": "6894a3b060c27baf53ab4cac"
  },
  "Aname": {
    "Name": "CHINEDU",
    "Mname": "",
    "Surname": "EKEZU"
  },
  "State": "",
  "LocalGovernment": "",
  "Sex": "",
  "Bloodgroup": "",
  "PhoneNumber": "",
  "EmergencyNo": "",
  "RegNo": "M25/029",
  "Validity": "2025-2027",
  "picturepath": "image/62250.jpg",
  "imgurl": "https://drive.google.com/file/d/1uZYGinMQrtyC_NBbeRU5eA3VM3BGxrzo/view?usp=drivesdk",
  "image": "https://lh3.googleusercontent.com/d/1uZYGinMQrtyC_NBbeRU5eA3VM3BGxrzo=s400?authuser=0",
  "time": "2025-08-07 13:01:36",
  "field": "fea532b9-ab43-49b8-9394-1bc5a77aa651",
  "id": 389,
  "__v": 0
},
{
  "_id": {
    "$oid": "6894a42a60c27baf53ab4cb5"
  },
  "Aname": {
    "Name": "TABITHA",
    "Mname": "ETIRE",
    "Surname": "MUBO"
  },
  "State": "",
  "LocalGovernment": "",
  "Sex": "",
  "Bloodgroup": "",
  "PhoneNumber": "",
  "EmergencyNo": "",
  "RegNo": "M25/047",
  "Validity": "2025-2027",
  "picturepath": "image/33396.jpg",
  "imgurl": "https://drive.google.com/file/d/1ebRWtS5weBpRXqmtCq9bqqgnp07zIcvd/view?usp=drivesdk",
  "image": "https://lh3.googleusercontent.com/d/1ebRWtS5weBpRXqmtCq9bqqgnp07zIcvd=s400?authuser=0",
  "time": "2025-08-07 13:03:38",
  "field": "86437f37-7185-4ae1-b5a9-797e2d766451",
  "id": 390,
  "__v": 0
},
{
  "_id": {
    "$oid": "6894a4e460c27baf53ab4cc4"
  },
  "Aname": {
    "Name": "OGU",
    "Mname": "",
    "Surname": "MARY"
  },
  "State": "",
  "LocalGovernment": "",
  "Sex": "",
  "Bloodgroup": "",
  "PhoneNumber": "",
  "EmergencyNo": "",
  "RegNo": "M25/108",
  "Validity": "2025-2027",
  "picturepath": "image/58451.jpg",
  "imgurl": "https://drive.google.com/file/d/11iikqaFRBtvVvz_zDOOzFMwBL86Jbo0i/view?usp=drivesdk",
  "image": "https://lh3.googleusercontent.com/d/11iikqaFRBtvVvz_zDOOzFMwBL86Jbo0i=s400?authuser=0",
  "time": "2025-08-07 13:06:44",
  "field": "cb64a89a-78cd-476a-925e-0f89b1c74985",
  "id": 391,
  "__v": 0
},
{
  "_id": {
    "$oid": "6894a52e60c27baf53ab4ccb"
  },
  "Aname": {
    "Name": "CHINEMEREM",
    "Mname": "",
    "Surname": "NWABUEZE"
  },
  "State": "",
  "LocalGovernment": "",
  "Sex": "",
  "Bloodgroup": "",
  "PhoneNumber": "",
  "EmergencyNo": "",
  "RegNo": "M25/062",
  "Validity": "2025-2027",
  "picturepath": "image/64159.jpg",
  "imgurl": "https://drive.google.com/file/d/1IrrPbVVwS1y80i6WLeriJFTG4q9Q1uFE/view?usp=drivesdk",
  "image": "https://lh3.googleusercontent.com/d/1IrrPbVVwS1y80i6WLeriJFTG4q9Q1uFE=s400?authuser=0",
  "time": "2025-08-07 13:07:58",
  "field": "feee6ac1-ffa1-428c-b9d3-ac3f3702f963",
  "id": 392,
  "__v": 0
},
{
  "_id": {
    "$oid": "6894a57560c27baf53ab4cd2"
  },
  "Aname": {
    "Name": "MIRIAN",
    "Mname": "JUNIOR",
    "Surname": "ONUEGBU"
  },
  "State": "",
  "LocalGovernment": "",
  "Sex": "",
  "Bloodgroup": "",
  "PhoneNumber": "",
  "EmergencyNo": "",
  "RegNo": "M25/077",
  "Validity": "2025-2027",
  "picturepath": "image/04199.jpg",
  "imgurl": "https://drive.google.com/file/d/1VCg24Cfdol2h7IXhfFZhIgcEmXovmw4l/view?usp=drivesdk",
  "image": "https://lh3.googleusercontent.com/d/1VCg24Cfdol2h7IXhfFZhIgcEmXovmw4l=s400?authuser=0",
  "time": "2025-08-07 13:09:09",
  "field": "d86844cc-a56f-4ca9-8878-f969b04a69bb",
  "id": 393,
  "__v": 0
},
{
  "_id": {
    "$oid": "6894a60460c27baf53ab4cd9"
  },
  "Aname": {
    "Name": "ONYINYECHI",
    "Mname": "GIFT",
    "Surname": "UZOMA"
  },
  "State": "",
  "LocalGovernment": "",
  "Sex": "",
  "Bloodgroup": "",
  "PhoneNumber": "",
  "EmergencyNo": "",
  "RegNo": "M25/093",
  "Validity": "2025-2027",
  "picturepath": "image/20404.jpg",
  "imgurl": "https://drive.google.com/file/d/1kl_1pMfllW2G3rWTtzOGQYdDI0620KjJ/view?usp=drivesdk",
  "image": "https://lh3.googleusercontent.com/d/1kl_1pMfllW2G3rWTtzOGQYdDI0620KjJ=s400?authuser=0",
  "time": "2025-08-07 13:11:32",
  "field": "d77922cb-b3b8-4009-a758-dfbc390c3438",
  "id": 394,
  "__v": 0
},
{
  "_id": {
    "$oid": "6894a65160c27baf53ab4ce2"
  },
  "Aname": {
    "Name": "MIRACLE",
    "Mname": "",
    "Surname": "MICHAEL"
  },
  "State": "",
  "LocalGovernment": "",
  "Sex": "",
  "Bloodgroup": "",
  "PhoneNumber": "",
  "EmergencyNo": "",
  "RegNo": "M25/109",
  "Validity": "2025-2027",
  "picturepath": "image/56130.jpg",
  "imgurl": "https://drive.google.com/file/d/1ceXOcA099JgUWzkLXx3NNQolpHhLmWrU/view?usp=drivesdk",
  "image": "https://lh3.googleusercontent.com/d/1ceXOcA099JgUWzkLXx3NNQolpHhLmWrU=s400?authuser=0",
  "time": "2025-08-07 13:12:49",
  "field": "5e2dc084-92f6-45a0-9a12-badba2e4334e",
  "id": 395,
  "__v": 0
},
{
  "_id": {
    "$oid": "6894a69260c27baf53ab4ce9"
  },
  "Aname": {
    "Name": "CONVENANT",
    "Mname": "",
    "Surname": "MAKIKPE"
  },
  "State": "",
  "LocalGovernment": "",
  "Sex": "",
  "Bloodgroup": "",
  "PhoneNumber": "",
  "EmergencyNo": "",
  "RegNo": "M25/049",
  "Validity": "2025-2027",
  "picturepath": "image/31318.jpg",
  "imgurl": "https://drive.google.com/file/d/14Zv83eMspeOqneqkNSNati4a2UpOQmSU/view?usp=drivesdk",
  "image": "https://lh3.googleusercontent.com/d/14Zv83eMspeOqneqkNSNati4a2UpOQmSU=s400?authuser=0",
  "time": "2025-08-07 13:13:54",
  "field": "c7ea3a00-faa0-465d-aec8-da47eb235265",
  "id": 396,
  "__v": 0
},
{
  "_id": {
    "$oid": "6894a6ca60c27baf53ab4cf0"
  },
  "Aname": {
    "Name": "SOPURUCHI",
    "Mname": "MARYANN",
    "Surname": "DIKE"
  },
  "State": "",
  "LocalGovernment": "",
  "Sex": "",
  "Bloodgroup": "",
  "PhoneNumber": "",
  "EmergencyNo": "",
  "RegNo": "M25/020",
  "Validity": "2025-2027",
  "picturepath": "image/45632.jpg",
  "imgurl": "https://drive.google.com/file/d/1ZVv0LNfYVleSpLi-dqlUva0knQe6AJbM/view?usp=drivesdk",
  "image": "https://lh3.googleusercontent.com/d/1ZVv0LNfYVleSpLi-dqlUva0knQe6AJbM=s400?authuser=0",
  "time": "2025-08-07 13:14:50",
  "field": "322279ee-7db0-40bb-930e-2342edb22656",
  "id": 397,
  "__v": 0
},
{
  "_id": {
    "$oid": "6894aa7160c27baf53ab4d07"
  },
  "Aname": {
    "Name": "VICTORIA",
    "Mname": "",
    "Surname": "EBOMUCHE"
  },
  "State": "",
  "LocalGovernment": "",
  "Sex": "",
  "Bloodgroup": "",
  "PhoneNumber": "",
  "EmergencyNo": "",
  "RegNo": "M25/022",
  "Validity": "2025-2027",
  "picturepath": "image/66595.jpg",
  "imgurl": "https://drive.google.com/file/d/1UYb6r0sINJJ8S52kvCgApByjax13TD2p/view?usp=drivesdk",
  "image": "https://lh3.googleusercontent.com/d/1UYb6r0sINJJ8S52kvCgApByjax13TD2p=s400?authuser=0",
  "time": "2025-08-07 13:30:25",
  "field": "a924c2e3-35a5-4595-91cf-ec6296fd268b",
  "id": 398,
  "__v": 0
},
{
  "_id": {
    "$oid": "6894aaaf60c27baf53ab4d0e"
  },
  "Aname": {
    "Name": "PRECIOUS",
    "Mname": "CHIAMAKA",
    "Surname": "SUNDAY"
  },
  "State": "",
  "LocalGovernment": "",
  "Sex": "",
  "Bloodgroup": "",
  "PhoneNumber": "",
  "EmergencyNo": "",
  "RegNo": "M25/089",
  "Validity": "2025-2027",
  "picturepath": "image/53865.jpg",
  "imgurl": "https://drive.google.com/file/d/1syyjpeDuB0SxO8kTIMNHjQGkG8T8V9vN/view?usp=drivesdk",
  "image": "https://lh3.googleusercontent.com/d/1syyjpeDuB0SxO8kTIMNHjQGkG8T8V9vN=s400?authuser=0",
  "time": "2025-08-07 13:31:27",
  "field": "6ab789fc-6d72-44b2-824d-ae754c8536c0",
  "id": 399,
  "__v": 0
},
{
  "_id": {
    "$oid": "6894aaf660c27baf53ab4d17"
  },
  "Aname": {
    "Name": "PEACE",
    "Mname": "NNENNA",
    "Surname": "OGUDU"
  },
  "State": "",
  "LocalGovernment": "",
  "Sex": "",
  "Bloodgroup": "",
  "PhoneNumber": "",
  "EmergencyNo": "",
  "RegNo": "M25/068",
  "Validity": "2025-2027",
  "picturepath": "image/82586.jpg",
  "imgurl": "https://drive.google.com/file/d/1J9iQyY1qKyiLTwze29qO9LchiDanUQSS/view?usp=drivesdk",
  "image": "https://lh3.googleusercontent.com/d/1J9iQyY1qKyiLTwze29qO9LchiDanUQSS=s400?authuser=0",
  "time": "2025-08-07 13:32:38",
  "field": "5d742753-a6a6-4555-a23f-7db3b028654f",
  "id": 400,
  "__v": 0
},
{
  "_id": {
    "$oid": "6894ab3d60c27baf53ab4d1e"
  },
  "Aname": {
    "Name": "CHINAECHEREM",
    "Mname": "",
    "Surname": "OHAEGBU"
  },
  "State": "",
  "LocalGovernment": "",
  "Sex": "",
  "Bloodgroup": "",
  "PhoneNumber": "",
  "EmergencyNo": "",
  "RegNo": "M25/103",
  "Validity": "2025-2027",
  "picturepath": "image/93339.jpg",
  "imgurl": "https://drive.google.com/file/d/1qtHaBOp_4YfVpnOU_TsEw0oWUKtEeSkX/view?usp=drivesdk",
  "image": "https://lh3.googleusercontent.com/d/1qtHaBOp_4YfVpnOU_TsEw0oWUKtEeSkX=s400?authuser=0",
  "time": "2025-08-07 13:33:49",
  "field": "d8bdb537-e836-41c1-9985-da5a26922155",
  "id": 401,
  "__v": 0
},
{
  "_id": {
    "$oid": "6894ab7660c27baf53ab4d25"
  },
  "Aname": {
    "Name": "CHIOMA",
    "Mname": "VIVIAN",
    "Surname": "ARUM"
  },
  "State": "",
  "LocalGovernment": "",
  "Sex": "",
  "Bloodgroup": "",
  "PhoneNumber": "",
  "EmergencyNo": "",
  "RegNo": "M25/013",
  "Validity": "2025-2027",
  "picturepath": "image/23331.jpg",
  "imgurl": "https://drive.google.com/file/d/1Z0_FrPpC-PpGWdsLmQdW-sHRV76oK7BP/view?usp=drivesdk",
  "image": "https://lh3.googleusercontent.com/d/1Z0_FrPpC-PpGWdsLmQdW-sHRV76oK7BP=s400?authuser=0",
  "time": "2025-08-07 13:34:46",
  "field": "7ff91e6a-a05b-4f4f-87ad-e8a6dcc679c2",
  "id": 402,
  "__v": 0
},
{
  "_id": {
    "$oid": "6894abb360c27baf53ab4d2c"
  },
  "Aname": {
    "Name": "ANGELA",
    "Mname": "CHINWENDU",
    "Surname": "EDWIN"
  },
  "State": "",
  "LocalGovernment": "",
  "Sex": "",
  "Bloodgroup": "",
  "PhoneNumber": "",
  "EmergencyNo": "",
  "RegNo": "M25/024",
  "Validity": "2025-2027",
  "picturepath": "image/25213.jpg",
  "imgurl": "https://drive.google.com/file/d/1bu4cOTTdeMXEEwKsG-p1HzcgLwKzt6pX/view?usp=drivesdk",
  "image": "https://lh3.googleusercontent.com/d/1bu4cOTTdeMXEEwKsG-p1HzcgLwKzt6pX=s400?authuser=0",
  "time": "2025-08-07 13:35:47",
  "field": "5b89b756-9bac-4a0a-a2c8-f285d38ed169",
  "id": 403,
  "__v": 0
},
{
  "_id": {
    "$oid": "6894ac2860c27baf53ab4d37"
  },
  "Aname": {
    "Name": "JULIET",
    "Mname": "",
    "Surname": "OPARA"
  },
  "State": "",
  "LocalGovernment": "",
  "Sex": "",
  "Bloodgroup": "",
  "PhoneNumber": "",
  "EmergencyNo": "",
  "RegNo": "M25/084",
  "Validity": "2025-2027",
  "picturepath": "image/66825.jpg",
  "imgurl": "https://drive.google.com/file/d/1TvoIFu1umA0zboofaxjhgRQYzAuktNFn/view?usp=drivesdk",
  "image": "https://lh3.googleusercontent.com/d/1TvoIFu1umA0zboofaxjhgRQYzAuktNFn=s400?authuser=0",
  "time": "2025-08-07 13:37:44",
  "field": "d92884d5-0a66-4baa-8df8-3ebecdbc6541",
  "id": 404,
  "__v": 0
},
{
  "_id": {
    "$oid": "6894daa84a3f34e1fb20d192"
  },
  "Aname": {
    "Name": "GIFT",
    "Mname": "",
    "Surname": "UZOMA"
  },
  "State": "",
  "LocalGovernment": "",
  "Sex": "",
  "Bloodgroup": "",
  "PhoneNumber": "",
  "EmergencyNo": "",
  "RegNo": "M25/098",
  "Validity": "2025-2027",
  "picturepath": "image/65529.jpg",
  "imgurl": "https://drive.google.com/file/d/1_Mn7B4Hy6z3noW5V-lqtI9NtH-hbKwlm/view?usp=drivesdk",
  "image": "https://lh3.googleusercontent.com/d/1_Mn7B4Hy6z3noW5V-lqtI9NtH-hbKwlm=s400?authuser=0",
  "time": "2025-08-07 16:56:08",
  "field": "b7dce287-aef1-4295-af3c-41770a64fbde",
  "id": 405,
  "__v": 0
},
{
  "_id": {
    "$oid": "6894dae24a3f34e1fb20d199"
  },
  "Aname": {
    "Name": "BLESSING",
    "Mname": "UCHECHI",
    "Surname": "OJINNAKA"
  },
  "State": "",
  "LocalGovernment": "",
  "Sex": "",
  "Bloodgroup": "",
  "PhoneNumber": "",
  "EmergencyNo": "",
  "RegNo": "M25/070",
  "Validity": "2025-2027",
  "picturepath": "image/32681.jpg",
  "imgurl": "https://drive.google.com/file/d/1p_sZl7KHRmZao8n8yps4R__ncjuaK8UP/view?usp=drivesdk",
  "image": "https://lh3.googleusercontent.com/d/1p_sZl7KHRmZao8n8yps4R__ncjuaK8UP=s400?authuser=0",
  "time": "2025-08-07 16:57:06",
  "field": "6f3078cb-e130-4fd9-a2ac-a8fb47d64193",
  "id": 406,
  "__v": 0
},
{
  "_id": {
    "$oid": "6894db1c4a3f34e1fb20d1a0"
  },
  "Aname": {
    "Name": "CYNTHIA",
    "Mname": "CHISOM",
    "Surname": "NWACHUKWU"
  },
  "State": "",
  "LocalGovernment": "",
  "Sex": "",
  "Bloodgroup": "",
  "PhoneNumber": "",
  "EmergencyNo": "",
  "RegNo": "M25/063",
  "Validity": "2025-2027",
  "picturepath": "image/32230.jpg",
  "imgurl": "https://drive.google.com/file/d/1-vod696lSRQE-_pc9oH9d6bvSE7Neqqg/view?usp=drivesdk",
  "image": "https://lh3.googleusercontent.com/d/1-vod696lSRQE-_pc9oH9d6bvSE7Neqqg=s400?authuser=0",
  "time": "2025-08-07 16:58:04",
  "field": "e32098f8-1b73-4432-881c-e1fe90ac4889",
  "id": 407,
  "__v": 0
},
{
  "_id": {
    "$oid": "6894db524a3f34e1fb20d1a7"
  },
  "Aname": {
    "Name": "PRECIOUS",
    "Mname": "CHONYERE",
    "Surname": "AGOH"
  },
  "State": "",
  "LocalGovernment": "",
  "Sex": "",
  "Bloodgroup": "",
  "PhoneNumber": "",
  "EmergencyNo": "",
  "RegNo": "M25/003",
  "Validity": "2025-2027",
  "picturepath": "image/88050.jpg",
  "imgurl": "https://drive.google.com/file/d/1al1zay7ykZtUkUhRgL4T9xlt3d9yOmzA/view?usp=drivesdk",
  "image": "https://lh3.googleusercontent.com/d/1al1zay7ykZtUkUhRgL4T9xlt3d9yOmzA=s400?authuser=0",
  "time": "2025-08-07 16:58:58",
  "field": "89f117c6-25a3-4787-980d-82f41807de9f",
  "id": 408,
  "__v": 0
},
{
  "_id": {
    "$oid": "6894db7b4a3f34e1fb20d1ae"
  },
  "Aname": {
    "Name": "FAVOUR",
    "Mname": "",
    "Surname": "BISHOP"
  },
  "State": "",
  "LocalGovernment": "",
  "Sex": "",
  "Bloodgroup": "",
  "PhoneNumber": "",
  "EmergencyNo": "",
  "RegNo": "M25/1000",
  "Validity": "2025-2027",
  "picturepath": "image/55009.jpg",
  "imgurl": "https://drive.google.com/file/d/1G-gVDBMIXXupAm8ArUw4tG3_l7yGSjZ2/view?usp=drivesdk",
  "image": "https://lh3.googleusercontent.com/d/1G-gVDBMIXXupAm8ArUw4tG3_l7yGSjZ2=s400?authuser=0",
  "time": "2025-08-07 16:59:39",
  "field": "504b5297-fecd-48cb-999a-2228fe0ac3c8",
  "id": 409,
  "__v": 0
},
{
  "_id": {
    "$oid": "6894dc484a3f34e1fb20d1b5"
  },
  "Aname": {
    "Name": "VICTORIA",
    "Mname": "NMESOMA",
    "Surname": "ARINZE"
  },
  "State": "",
  "LocalGovernment": "",
  "Sex": "",
  "Bloodgroup": "",
  "PhoneNumber": "",
  "EmergencyNo": "",
  "RegNo": "M25/101",
  "Validity": "2025-2027",
  "picturepath": "image/41302.jpg",
  "imgurl": "https://drive.google.com/file/d/1koOA3WfNMDq4m0Yepc0rr2isvFsEvyhK/view?usp=drivesdk",
  "image": "https://lh3.googleusercontent.com/d/1koOA3WfNMDq4m0Yepc0rr2isvFsEvyhK=s400?authuser=0",
  "time": "2025-08-07 17:03:04",
  "field": "6d301376-2016-409f-8079-f0ee504019ce",
  "id": 410,
  "__v": 0
},
{
  "_id": {
    "$oid": "6894dc7b4a3f34e1fb20d1bc"
  },
  "Aname": {
    "Name": "BLESSING",
    "Mname": "NGOZIKA",
    "Surname": "NWACHUKWU"
  },
  "State": "",
  "LocalGovernment": "",
  "Sex": "",
  "Bloodgroup": "",
  "PhoneNumber": "",
  "EmergencyNo": "",
  "RegNo": "M25/102",
  "Validity": "2025-2027",
  "picturepath": "image/20385.jpg",
  "imgurl": "https://drive.google.com/file/d/1JZm6-MKqVlgk3RBgxgxra87jfVqqc7kk/view?usp=drivesdk",
  "image": "https://lh3.googleusercontent.com/d/1JZm6-MKqVlgk3RBgxgxra87jfVqqc7kk=s400?authuser=0",
  "time": "2025-08-07 17:03:55",
  "field": "1fc7886f-c808-49be-b101-25eaeffa9dd1",
  "id": 411,
  "__v": 0
},
{
  "_id": {
    "$oid": "6894dcaa4a3f34e1fb20d1c3"
  },
  "Aname": {
    "Name": "CHINAZA",
    "Mname": "JOY",
    "Surname": "OKEREKE"
  },
  "State": "",
  "LocalGovernment": "",
  "Sex": "",
  "Bloodgroup": "",
  "PhoneNumber": "",
  "EmergencyNo": "",
  "RegNo": "M25/104",
  "Validity": "2025-2027",
  "picturepath": "image/65396.jpg",
  "imgurl": "https://drive.google.com/file/d/1hNT78hjKaGiY9ERYzqjDIo0ofCcjAXKD/view?usp=drivesdk",
  "image": "https://lh3.googleusercontent.com/d/1hNT78hjKaGiY9ERYzqjDIo0ofCcjAXKD=s400?authuser=0",
  "time": "2025-08-07 17:04:42",
  "field": "0fdc128f-c232-4fb0-965f-cc4a81a95cc1",
  "id": 412,
  "__v": 0
},
{
  "_id": {
    "$oid": "6894dd424a3f34e1fb20d1ca"
  },
  "Aname": {
    "Name": "PRECIOUS",
    "Mname": "",
    "Surname": "IGWE"
  },
  "State": "",
  "LocalGovernment": "",
  "Sex": "",
  "Bloodgroup": "",
  "PhoneNumber": "",
  "EmergencyNo": "",
  "RegNo": "M25/105",
  "Validity": "2025-2027",
  "picturepath": "image/95565.jpg",
  "imgurl": "https://drive.google.com/file/d/163b0wfcZ_nCqzfhpXT8rRwY6d7Ugg3ln/view?usp=drivesdk",
  "image": "https://lh3.googleusercontent.com/d/163b0wfcZ_nCqzfhpXT8rRwY6d7Ugg3ln=s400?authuser=0",
  "time": "2025-08-07 17:07:14",
  "field": "cce68d1d-32ac-4b02-8d3d-4386420860b3",
  "id": 413,
  "__v": 0
},
{
  "_id": {
    "$oid": "6894dd724a3f34e1fb20d1d1"
  },
  "Aname": {
    "Name": "V8CTORY",
    "Mname": "",
    "Surname": "ONWUAMANAM"
  },
  "State": "",
  "LocalGovernment": "",
  "Sex": "",
  "Bloodgroup": "",
  "PhoneNumber": "",
  "EmergencyNo": "",
  "RegNo": "M25/106",
  "Validity": "2025-2027",
  "picturepath": "image/10206.jpg",
  "imgurl": "https://drive.google.com/file/d/1iQO10eDXQSGJkhGvf5CsLEWDhsF8OcyT/view?usp=drivesdk",
  "image": "https://lh3.googleusercontent.com/d/1iQO10eDXQSGJkhGvf5CsLEWDhsF8OcyT=s400?authuser=0",
  "time": "2025-08-07 17:08:02",
  "field": "b7802f8a-1f47-4dfb-9979-cdf001460fcd",
  "id": 414,
  "__v": 0
},
{
  "_id": {
    "$oid": "6894ddab4a3f34e1fb20d1d8"
  },
  "Aname": {
    "Name": "ANGELINA",
    "Mname": "",
    "Surname": "NWACHUKWU"
  },
  "State": "",
  "LocalGovernment": "",
  "Sex": "",
  "Bloodgroup": "",
  "PhoneNumber": "",
  "EmergencyNo": "",
  "RegNo": "M25/107",
  "Validity": "2025-2027",
  "picturepath": "image/12103.jpg",
  "imgurl": "https://drive.google.com/file/d/1rPcw-rKhTf8IQ9zgRUAk7ULORt5dafOZ/view?usp=drivesdk",
  "image": "https://lh3.googleusercontent.com/d/1rPcw-rKhTf8IQ9zgRUAk7ULORt5dafOZ=s400?authuser=0",
  "time": "2025-08-07 17:08:59",
  "field": "16ad624b-ef57-43fd-aa6b-2eefb6eb7a71",
  "id": 415,
  "__v": 0
},
{
  "_id": {
    "$oid": "6894dde04a3f34e1fb20d1df"
  },
  "Aname": {
    "Name": "ANGELA",
    "Mname": "UCHECHI",
    "Surname": "ONWENU"
  },
  "State": "",
  "LocalGovernment": "",
  "Sex": "",
  "Bloodgroup": "",
  "PhoneNumber": "",
  "EmergencyNo": "",
  "RegNo": "M25/080",
  "Validity": "2025-2027",
  "picturepath": "image/89561.jpg",
  "imgurl": "https://drive.google.com/file/d/142OVk2TS1oHAXZabyZ1tvzA4W71kIY1d/view?usp=drivesdk",
  "image": "https://lh3.googleusercontent.com/d/142OVk2TS1oHAXZabyZ1tvzA4W71kIY1d=s400?authuser=0",
  "time": "2025-08-07 17:09:52",
  "field": "cf8f4cc8-a1f2-4f9b-a1ed-cd327d54aae1",
  "id": 416,
  "__v": 0
},
{
  "_id": {
    "$oid": "6894de0c4a3f34e1fb20d1e6"
  },
  "Aname": {
    "Name": "CHINAZA",
    "Mname": "VIVIAN",
    "Surname": "NDUBUISI"
  },
  "State": "",
  "LocalGovernment": "",
  "Sex": "",
  "Bloodgroup": "",
  "PhoneNumber": "",
  "EmergencyNo": "",
  "RegNo": "M25/054",
  "Validity": "2025-2027",
  "picturepath": "image/23850.jpg",
  "imgurl": "https://drive.google.com/file/d/1907sJ7w2VYOraRCJzkUw-nArVRPYWj1S/view?usp=drivesdk",
  "image": "https://lh3.googleusercontent.com/d/1907sJ7w2VYOraRCJzkUw-nArVRPYWj1S=s400?authuser=0",
  "time": "2025-08-07 17:10:36",
  "field": "7c7e12a7-34c7-4d97-800c-036c1d30b00a",
  "id": 417,
  "__v": 0
},
{
  "_id": {
    "$oid": "6894de464a3f34e1fb20d1ed"
  },
  "Aname": {
    "Name": "ROSEMARY",
    "Mname": "",
    "Surname": "OPARA"
  },
  "State": "",
  "LocalGovernment": "",
  "Sex": "",
  "Bloodgroup": "",
  "PhoneNumber": "",
  "EmergencyNo": "",
  "RegNo": "M25/086",
  "Validity": "2025-2027",
  "picturepath": "image/96681.jpg",
  "imgurl": "https://drive.google.com/file/d/1alVhKxamugXCdmfvnp4sYGuYo_JR8orh/view?usp=drivesdk",
  "image": "https://lh3.googleusercontent.com/d/1alVhKxamugXCdmfvnp4sYGuYo_JR8orh=s400?authuser=0",
  "time": "2025-08-07 17:11:34",
  "field": "77c12051-b5dc-44a8-a174-26a1a8ac701a",
  "id": 418,
  "__v": 0
},
{
  "_id": {
    "$oid": "6894de8f4a3f34e1fb20d1f6"
  },
  "Aname": {
    "Name": "MMESOMA",
    "Mname": "PRECIOUS",
    "Surname": "EZEAGU"
  },
  "State": "",
  "LocalGovernment": "",
  "Sex": "",
  "Bloodgroup": "",
  "PhoneNumber": "",
  "EmergencyNo": "",
  "RegNo": "M25/036",
  "Validity": "2025-2027",
  "picturepath": "image/91038.jpg",
  "imgurl": "https://drive.google.com/file/d/1oJcVdEzVlGIeDT0tSou8pa12LvJbuM7F/view?usp=drivesdk",
  "image": "https://lh3.googleusercontent.com/d/1oJcVdEzVlGIeDT0tSou8pa12LvJbuM7F=s400?authuser=0",
  "time": "2025-08-07 17:12:47",
  "field": "eb0f017c-e6b8-4017-888e-c2e45673dd2f",
  "id": 419,
  "__v": 0
},
{
  "_id": {
    "$oid": "6894df617dc524115b3e79d3"
  },
  "Aname": {
    "Name": "CHIKWE",
    "Mname": "",
    "Surname": "DIVINE"
  },
  "State": "",
  "LocalGovernment": "",
  "Sex": "",
  "Bloodgroup": "",
  "PhoneNumber": "",
  "EmergencyNo": "",
  "RegNo": "M25/016",
  "Validity": "2025-2027",
  "picturepath": "image/10886.jpg",
  "imgurl": "https://drive.google.com/file/d/1mUJSqsTo3Z62am7CTmZOADWx9GizNVwe/view?usp=drivesdk",
  "image": "https://lh3.googleusercontent.com/d/1mUJSqsTo3Z62am7CTmZOADWx9GizNVwe=s400?authuser=0",
  "time": "2025-08-07 17:16:17",
  "field": "c1c2be71-4ef9-41d9-94c9-b9fe758230c4",
  "id": 421,
  "__v": 0
},
{
  "_id": {
    "$oid": "6894dfad7dc524115b3e79dc"
  },
  "Aname": {
    "Name": "VERA",
    "Mname": "",
    "Surname": "ONYA"
  },
  "State": "",
  "LocalGovernment": "",
  "Sex": "",
  "Bloodgroup": "",
  "PhoneNumber": "",
  "EmergencyNo": "",
  "RegNo": "M25/082",
  "Validity": "2025-2027",
  "picturepath": "image/88350.jpg",
  "imgurl": "https://drive.google.com/file/d/1gBpQu5ptNgJKpR5iB87zu9086bGhwAYo/view?usp=drivesdk",
  "image": "https://lh3.googleusercontent.com/d/1gBpQu5ptNgJKpR5iB87zu9086bGhwAYo=s400?authuser=0",
  "time": "2025-08-07 17:17:33",
  "field": "c68979d0-c16e-48b0-85c2-27bbd837b46b",
  "id": 422,
  "__v": 0
},
{
  "_id": {
    "$oid": "6895afc04bdb8afcd5386384"
  },
  "Aname": {
    "Name": "CHIZITERE",
    "Mname": "",
    "Surname": "ARUNONYE"
  },
  "State": "",
  "LocalGovernment": "",
  "Sex": "",
  "Bloodgroup": "",
  "PhoneNumber": "",
  "EmergencyNo": "",
  "RegNo": "M25/012",
  "Validity": "2025-2027",
  "picturepath": "image/46525.jpg",
  "imgurl": "https://drive.google.com/file/d/1rQzyMo-rN6-IJE4wfQwMJanVO7uDv-p6/view?usp=drivesdk",
  "image": "https://lh3.googleusercontent.com/d/1rQzyMo-rN6-IJE4wfQwMJanVO7uDv-p6=s400?authuser=0",
  "time": "2025-08-08 08:05:20",
  "field": "3034793e-6ea7-4d81-ad9c-5e2713efa861",
  "id": 423,
  "__v": 0
},
{
  "_id": {
    "$oid": "6895afee4bdb8afcd538638b"
  },
  "Aname": {
    "Name": "PRECIOUS",
    "Mname": "",
    "Surname": "EKENE"
  },
  "State": "",
  "LocalGovernment": "",
  "Sex": "",
  "Bloodgroup": "",
  "PhoneNumber": "",
  "EmergencyNo": "",
  "RegNo": "M25/027",
  "Validity": "2025-2027",
  "picturepath": "image/31393.jpg",
  "imgurl": "https://drive.google.com/file/d/1Ix6ZMQWwLVrX4EwfbN2wW6-dg2bMJ5Aa/view?usp=drivesdk",
  "image": "https://lh3.googleusercontent.com/d/1Ix6ZMQWwLVrX4EwfbN2wW6-dg2bMJ5Aa=s400?authuser=0",
  "time": "2025-08-08 08:06:06",
  "field": "4b6b3454-1dc7-44db-b92f-35696f0f90ad",
  "id": 424,
  "__v": 0
},
{
  "_id": {
    "$oid": "6895b0274bdb8afcd5386392"
  },
  "Aname": {
    "Name": "EZINNE",
    "Mname": "",
    "Surname": "AGUOCHA"
  },
  "State": "",
  "LocalGovernment": "",
  "Sex": "",
  "Bloodgroup": "",
  "PhoneNumber": "",
  "EmergencyNo": "",
  "RegNo": "M25/004",
  "Validity": "2025-2027",
  "picturepath": "image/30199.jpg",
  "imgurl": "https://drive.google.com/file/d/1-gYmspdR1UVnncnujw4iQPScptv5c54r/view?usp=drivesdk",
  "image": "https://lh3.googleusercontent.com/d/1-gYmspdR1UVnncnujw4iQPScptv5c54r=s400?authuser=0",
  "time": "2025-08-08 08:07:03",
  "field": "3142ca8d-c267-40d6-8d93-e952207ef5e6",
  "id": 425,
  "__v": 0
},
{
  "_id": {
    "$oid": "6895b0614bdb8afcd5386399"
  },
  "Aname": {
    "Name": "CHIOMA",
    "Mname": "PRAISE",
    "Surname": "IHEANACHO"
  },
  "State": "",
  "LocalGovernment": "",
  "Sex": "",
  "Bloodgroup": "",
  "PhoneNumber": "",
  "EmergencyNo": "",
  "RegNo": "M25/044",
  "Validity": "2025-2027",
  "picturepath": "image/02132.jpg",
  "imgurl": "https://drive.google.com/file/d/1g68ODg5xxjeUI9NGXNEzSan2z3Opu8aX/view?usp=drivesdk",
  "image": "https://lh3.googleusercontent.com/d/1g68ODg5xxjeUI9NGXNEzSan2z3Opu8aX=s400?authuser=0",
  "time": "2025-08-08 08:08:01",
  "field": "1032e5e4-b188-41d8-854c-2437a1af20e4",
  "id": 426,
  "__v": 0
},
{
  "_id": {
    "$oid": "6895b0984bdb8afcd53863a0"
  },
  "Aname": {
    "Name": "HAPPINESS",
    "Mname": "",
    "Surname": "ABARAONYE"
  },
  "State": "",
  "LocalGovernment": "",
  "Sex": "",
  "Bloodgroup": "",
  "PhoneNumber": "",
  "EmergencyNo": "",
  "RegNo": "M25/001",
  "Validity": "2025-2027",
  "picturepath": "image/59831.jpg",
  "imgurl": "https://drive.google.com/file/d/176sFQS_f8xIbydkImaK48JqLl3o0RNUa/view?usp=drivesdk",
  "image": "https://lh3.googleusercontent.com/d/176sFQS_f8xIbydkImaK48JqLl3o0RNUa=s400?authuser=0",
  "time": "2025-08-08 08:08:56",
  "field": "225cc0e9-1bfa-418e-9f58-4069a84da758",
  "id": 427,
  "__v": 0
},
{
  "_id": {
    "$oid": "6895b0ca4bdb8afcd53863a7"
  },
  "Aname": {
    "Name": "TRACY",
    "Mname": "AMARACHI",
    "Surname": "AZUBUIKE"
  },
  "State": "",
  "LocalGovernment": "",
  "Sex": "",
  "Bloodgroup": "",
  "PhoneNumber": "",
  "EmergencyNo": "",
  "RegNo": "M25/015",
  "Validity": "2025-2027",
  "picturepath": "image/84015.jpg",
  "imgurl": "https://drive.google.com/file/d/16Dz5Mi2BY0he29kVPDZObs5NLg_Kmj5o/view?usp=drivesdk",
  "image": "https://lh3.googleusercontent.com/d/16Dz5Mi2BY0he29kVPDZObs5NLg_Kmj5o=s400?authuser=0",
  "time": "2025-08-08 08:09:46",
  "field": "b3fdeb49-8250-4cff-8384-a1c87738dbda",
  "id": 428,
  "__v": 0
},
{
  "_id": {
    "$oid": "6895b0fc4bdb8afcd53863ae"
  },
  "Aname": {
    "Name": "MELODY",
    "Mname": "ONYINYECHI",
    "Surname": "PROMISE"
  },
  "State": "",
  "LocalGovernment": "",
  "Sex": "",
  "Bloodgroup": "",
  "PhoneNumber": "",
  "EmergencyNo": "",
  "RegNo": "M25/088",
  "Validity": "2025-2027",
  "picturepath": "image/24140.jpg",
  "imgurl": "https://drive.google.com/file/d/17vk3KbZWLePNMrkDVKCYYMrE48gl9ox-/view?usp=drivesdk",
  "image": "https://lh3.googleusercontent.com/d/17vk3KbZWLePNMrkDVKCYYMrE48gl9ox-=s400?authuser=0",
  "time": "2025-08-08 08:10:36",
  "field": "2c4d4b74-78c9-4e52-a974-9e0e3ff3c9b8",
  "id": 429,
  "__v": 0
},
{
  "_id": {
    "$oid": "6895b12e4bdb8afcd53863b5"
  },
  "Aname": {
    "Name": "VIVIAN",
    "Mname": "CHIZARAM",
    "Surname": "ANENE"
  },
  "State": "",
  "LocalGovernment": "",
  "Sex": "",
  "Bloodgroup": "",
  "PhoneNumber": "",
  "EmergencyNo": "",
  "RegNo": "M25/009",
  "Validity": "2025-2027",
  "picturepath": "image/89538.jpg",
  "imgurl": "https://drive.google.com/file/d/1WDrU43hcBfFbj-Xm7SX_YKR8keglf9sE/view?usp=drivesdk",
  "image": "https://lh3.googleusercontent.com/d/1WDrU43hcBfFbj-Xm7SX_YKR8keglf9sE=s400?authuser=0",
  "time": "2025-08-08 08:11:26",
  "field": "1761d87b-9c81-459e-ba3a-0a3934539c26",
  "id": 430,
  "__v": 0
},
{
  "_id": {
    "$oid": "6895b15f4bdb8afcd53863bc"
  },
  "Aname": {
    "Name": "BLESSING",
    "Mname": "",
    "Surname": "ANTHONY"
  },
  "State": "",
  "LocalGovernment": "",
  "Sex": "",
  "Bloodgroup": "",
  "PhoneNumber": "",
  "EmergencyNo": "",
  "RegNo": "M25/010",
  "Validity": "2025-2027",
  "picturepath": "image/58148.jpg",
  "imgurl": "https://drive.google.com/file/d/1GAB68zb0I1eXAt9dDq-BYvOfmWBSw6ZN/view?usp=drivesdk",
  "image": "https://lh3.googleusercontent.com/d/1GAB68zb0I1eXAt9dDq-BYvOfmWBSw6ZN=s400?authuser=0",
  "time": "2025-08-08 08:12:15",
  "field": "302096e7-7329-4ee4-96b4-a335e5bf4461",
  "id": 431,
  "__v": 0
},
{
  "_id": {
    "$oid": "6895b1954bdb8afcd53863c3"
  },
  "Aname": {
    "Name": "DELIGHT",
    "Mname": "",
    "Surname": "WILLIAMS"
  },
  "State": "",
  "LocalGovernment": "",
  "Sex": "",
  "Bloodgroup": "",
  "PhoneNumber": "",
  "EmergencyNo": "",
  "RegNo": "M25/099",
  "Validity": "2025-2027",
  "picturepath": "image/06245.jpg",
  "imgurl": "https://drive.google.com/file/d/1bQntY9pDSLhXvvdVIjhJN1Rr5m13C1Dv/view?usp=drivesdk",
  "image": "https://lh3.googleusercontent.com/d/1bQntY9pDSLhXvvdVIjhJN1Rr5m13C1Dv=s400?authuser=0",
  "time": "2025-08-08 08:13:09",
  "field": "425174be-9033-4e9a-98c7-5bbc7187a861",
  "id": 432,
  "__v": 0
},
{
  "_id": {
    "$oid": "6895b1de4bdb8afcd53863ca"
  },
  "Aname": {
    "Name": "CHIZITERE",
    "Mname": "",
    "Surname": "ANUONYE"
  },
  "State": "",
  "LocalGovernment": "",
  "Sex": "",
  "Bloodgroup": "",
  "PhoneNumber": "",
  "EmergencyNo": "",
  "RegNo": "M24012",
  "Validity": "2024-2026",
  "picturepath": "image/03588.jpg",
  "imgurl": "https://drive.google.com/file/d/1cCU33iUC635N_CrNK58t3U1ntCWmNat7/view?usp=drivesdk",
  "image": "https://lh3.googleusercontent.com/d/1cCU33iUC635N_CrNK58t3U1ntCWmNat7=s400?authuser=0",
  "time": "2025-08-08 08:14:22",
  "field": "e15929cb-90a1-4ef8-bdb8-72ca82421038",
  "id": 433,
  "__v": 0
},
{
  "_id": {
    "$oid": "6895b20d4bdb8afcd53863d1"
  },
  "Aname": {
    "Name": "FAITH",
    "Mname": "",
    "Surname": "EDMOND"
  },
  "State": "",
  "LocalGovernment": "",
  "Sex": "",
  "Bloodgroup": "",
  "PhoneNumber": "",
  "EmergencyNo": "",
  "RegNo": "M25/023",
  "Validity": "2025-2027",
  "picturepath": "image/90915.jpg",
  "imgurl": "https://drive.google.com/file/d/1tuYpTftBUZhKa8Tsm0izFmf2xxvj87Z6/view?usp=drivesdk",
  "image": "https://lh3.googleusercontent.com/d/1tuYpTftBUZhKa8Tsm0izFmf2xxvj87Z6=s400?authuser=0",
  "time": "2025-08-08 08:15:09",
  "field": "53615f4f-3270-4396-b2a0-947cbdb98ea0",
  "id": 434,
  "__v": 0
},
{
  "_id": {
    "$oid": "6895b2404bdb8afcd53863d8"
  },
  "Aname": {
    "Name": "JOY",
    "Mname": "CHINAEMEREM",
    "Surname": "EJIKEME"
  },
  "State": "",
  "LocalGovernment": "",
  "Sex": "",
  "Bloodgroup": "",
  "PhoneNumber": "",
  "EmergencyNo": "",
  "RegNo": "M25/025",
  "Validity": "2025-2027",
  "picturepath": "image/83982.jpg",
  "imgurl": "https://drive.google.com/file/d/1KsidLZAV-Dac7FHgCVRfUafaCt9EEw7F/view?usp=drivesdk",
  "image": "https://lh3.googleusercontent.com/d/1KsidLZAV-Dac7FHgCVRfUafaCt9EEw7F=s400?authuser=0",
  "time": "2025-08-08 08:16:00",
  "field": "2c2a3753-21db-454c-9270-a094efae064d",
  "id": 435,
  "__v": 0
},
{
  "_id": {
    "$oid": "6895b2784bdb8afcd53863df"
  },
  "Aname": {
    "Name": "JACINTA",
    "Mname": "",
    "Surname": "AKALONU"
  },
  "State": "",
  "LocalGovernment": "",
  "Sex": "",
  "Bloodgroup": "",
  "PhoneNumber": "",
  "EmergencyNo": "",
  "RegNo": "M25/005",
  "Validity": "2025-2027",
  "picturepath": "image/24141.jpg",
  "imgurl": "https://drive.google.com/file/d/1oq7XQQUQyEEUe4sQdn0k-VKDlfSy-9bn/view?usp=drivesdk",
  "image": "https://lh3.googleusercontent.com/d/1oq7XQQUQyEEUe4sQdn0k-VKDlfSy-9bn=s400?authuser=0",
  "time": "2025-08-08 08:16:56",
  "field": "aecda873-0c39-4935-a341-d60aeba0d9c9",
  "id": 436,
  "__v": 0
},
{
  "_id": {
    "$oid": "6895b4174bdb8afcd53863e8"
  },
  "Aname": {
    "Name": "CHISOM",
    "Mname": "FAVOUR",
    "Surname": "OHALETE"
  },
  "State": "",
  "LocalGovernment": "",
  "Sex": "",
  "Bloodgroup": "",
  "PhoneNumber": "",
  "EmergencyNo": "",
  "RegNo": "M25/069",
  "Validity": "2025-2027",
  "picturepath": "image/18913.jpg",
  "imgurl": "https://drive.google.com/file/d/1xY_rpLvDTvxu5jhUY2SkICWd-SfSlsui/view?usp=drivesdk",
  "image": "https://lh3.googleusercontent.com/d/1xY_rpLvDTvxu5jhUY2SkICWd-SfSlsui=s400?authuser=0",
  "time": "2025-08-08 08:23:51",
  "field": "207699bd-5e4a-49af-9506-0f0a86375fb8",
  "id": 437,
  "__v": 0
},
{
  "_id": {
    "$oid": "6895b44d4bdb8afcd53863f1"
  },
  "Aname": {
    "Name": "PRECIOUS",
    "Mname": "",
    "Surname": "NWABEKE"
  },
  "State": "",
  "LocalGovernment": "",
  "Sex": "",
  "Bloodgroup": "",
  "PhoneNumber": "",
  "EmergencyNo": "",
  "RegNo": "M25/061",
  "Validity": "2025-2027",
  "picturepath": "image/29554.jpg",
  "imgurl": "https://drive.google.com/file/d/11E3FTPZhRI7F65GMP9IaEVMe6avJtKfI/view?usp=drivesdk",
  "image": "https://lh3.googleusercontent.com/d/11E3FTPZhRI7F65GMP9IaEVMe6avJtKfI=s400?authuser=0",
  "time": "2025-08-08 08:24:45",
  "field": "4982ec32-2bcc-4b6d-9f8c-69e9df4f41d4",
  "id": 438,
  "__v": 0
},
{
  "_id": {
    "$oid": "6895b4834bdb8afcd53863f8"
  },
  "Aname": {
    "Name": "JACINTA",
    "Mname": "",
    "Surname": "OLONLWO"
  },
  "State": "",
  "LocalGovernment": "",
  "Sex": "",
  "Bloodgroup": "",
  "PhoneNumber": "",
  "EmergencyNo": "",
  "RegNo": "M25/072",
  "Validity": "2025-2027",
  "picturepath": "image/48530.jpg",
  "imgurl": "https://drive.google.com/file/d/15EQZ4rP_lq-qy69sR3_wbhMX-FNwisfD/view?usp=drivesdk",
  "image": "https://lh3.googleusercontent.com/d/15EQZ4rP_lq-qy69sR3_wbhMX-FNwisfD=s400?authuser=0",
  "time": "2025-08-08 08:25:39",
  "field": "de6f9195-85a1-48fb-a30c-751882e61b43",
  "id": 439,
  "__v": 0
},
{
  "_id": {
    "$oid": "6895b4d14bdb8afcd5386401"
  },
  "Aname": {
    "Name": "FAVOUR",
    "Mname": "CHIAMAKA",
    "Surname": "AHGWO"
  },
  "State": "",
  "LocalGovernment": "",
  "Sex": "",
  "Bloodgroup": "",
  "PhoneNumber": "",
  "EmergencyNo": "",
  "RegNo": "M25/006",
  "Validity": "2025-2027",
  "picturepath": "image/60054.jpg",
  "imgurl": "https://drive.google.com/file/d/1RDgUggnDwYc_ED3dOAY7E5ke2_DGd-vx/view?usp=drivesdk",
  "image": "https://lh3.googleusercontent.com/d/1RDgUggnDwYc_ED3dOAY7E5ke2_DGd-vx=s400?authuser=0",
  "time": "2025-08-08 08:26:57",
  "field": "e4b7c24e-2ef3-4b8d-b262-2ff1d71a80b0",
  "id": 440,
  "__v": 0
},
{
  "_id": {
    "$oid": "6895b50e4bdb8afcd5386408"
  },
  "Aname": {
    "Name": "CHINAECHEREM",
    "Mname": "",
    "Surname": "ONYENAECHERRM"
  },
  "State": "",
  "LocalGovernment": "",
  "Sex": "",
  "Bloodgroup": "",
  "PhoneNumber": "",
  "EmergencyNo": "",
  "RegNo": "M25/081",
  "Validity": "2025-2027",
  "picturepath": "image/23860.jpg",
  "imgurl": "https://drive.google.com/file/d/1B2GdDxCBALr29QlicIy3nGELpI7YD4_E/view?usp=drivesdk",
  "image": "https://lh3.googleusercontent.com/d/1B2GdDxCBALr29QlicIy3nGELpI7YD4_E=s400?authuser=0",
  "time": "2025-08-08 08:27:58",
  "field": "8e847682-9261-448d-ba4c-0d8ea52aed07",
  "id": 441,
  "__v": 0
},
{
  "_id": {
    "$oid": "6895b5404bdb8afcd538640f"
  },
  "Aname": {
    "Name": "PRECIOUS",
    "Mname": "",
    "Surname": "ENWURU"
  },
  "State": "",
  "LocalGovernment": "",
  "Sex": "",
  "Bloodgroup": "",
  "PhoneNumber": "",
  "EmergencyNo": "",
  "RegNo": "M25/034",
  "Validity": "2025-2027",
  "picturepath": "image/50460.jpg",
  "imgurl": "https://drive.google.com/file/d/18-JLyNukgIpkQF8l_iZU-70y8byYNSFR/view?usp=drivesdk",
  "image": "https://lh3.googleusercontent.com/d/18-JLyNukgIpkQF8l_iZU-70y8byYNSFR=s400?authuser=0",
  "time": "2025-08-08 08:28:48",
  "field": "b3a73fdf-f237-4426-84fa-8109d01f3b8b",
  "id": 442,
  "__v": 0
},
{
  "_id": {
    "$oid": "6895b5714bdb8afcd5386416"
  },
  "Aname": {
    "Name": "PATIENCE",
    "Mname": "CHIDINMA",
    "Surname": "NJOKU"
  },
  "State": "",
  "LocalGovernment": "",
  "Sex": "",
  "Bloodgroup": "",
  "PhoneNumber": "",
  "EmergencyNo": "",
  "RegNo": "M25/056",
  "Validity": "2025-2027",
  "picturepath": "image/15551.jpg",
  "imgurl": "https://drive.google.com/file/d/1JBSiRN9D7TJg7lLnThCMLsxE6K2yriYN/view?usp=drivesdk",
  "image": "https://lh3.googleusercontent.com/d/1JBSiRN9D7TJg7lLnThCMLsxE6K2yriYN=s400?authuser=0",
  "time": "2025-08-08 08:29:37",
  "field": "eb7a3b96-f95b-408e-a778-183b078d24b0",
  "id": 443,
  "__v": 0
},
{
  "_id": {
    "$oid": "6895b5aa4bdb8afcd538641d"
  },
  "Aname": {
    "Name": "BLESSING",
    "Mname": "CHIDERA",
    "Surname": "ANOKA"
  },
  "State": "",
  "LocalGovernment": "",
  "Sex": "",
  "Bloodgroup": "",
  "PhoneNumber": "",
  "EmergencyNo": "",
  "RegNo": "M25/011",
  "Validity": "2025-2027",
  "picturepath": "image/01225.jpg",
  "imgurl": "https://drive.google.com/file/d/1oC1VefdBqMHkJBU0EQR1xdJv4K9pUGR_/view?usp=drivesdk",
  "image": "https://lh3.googleusercontent.com/d/1oC1VefdBqMHkJBU0EQR1xdJv4K9pUGR_=s400?authuser=0",
  "time": "2025-08-08 08:30:34",
  "field": "e2e90df5-ec39-49c4-aded-b7a6f6f0ac31",
  "id": 444,
  "__v": 0
},
{
  "_id": {
    "$oid": "6895b5da4bdb8afcd5386424"
  },
  "Aname": {
    "Name": "PRECIOUS",
    "Mname": "",
    "Surname": "IREGBU"
  },
  "State": "",
  "LocalGovernment": "",
  "Sex": "",
  "Bloodgroup": "",
  "PhoneNumber": "",
  "EmergencyNo": "",
  "RegNo": "M24",
  "Validity": "2024-2026",
  "picturepath": "image/69964.jpg",
  "imgurl": "https://drive.google.com/file/d/1fjFLWntaIYf1yvQyw7mkipqToKmOZIyf/view?usp=drivesdk",
  "image": "https://lh3.googleusercontent.com/d/1fjFLWntaIYf1yvQyw7mkipqToKmOZIyf=s400?authuser=0",
  "time": "2025-08-08 08:31:22",
  "field": "be7dbdeb-a442-4299-b715-9db0b8b38173",
  "id": 445,
  "__v": 0
},
{
  "_id": {
    "$oid": "6895b6064bdb8afcd538642b"
  },
  "Aname": {
    "Name": "VIVIAN",
    "Mname": "",
    "Surname": "EKEWANEZE"
  },
  "State": "",
  "LocalGovernment": "",
  "Sex": "",
  "Bloodgroup": "",
  "PhoneNumber": "",
  "EmergencyNo": "",
  "RegNo": "M25/028",
  "Validity": "2025-2027",
  "picturepath": "image/68280.jpg",
  "imgurl": "https://drive.google.com/file/d/18BemDPwA123WwMCubSsMoU2hPal00xXJ/view?usp=drivesdk",
  "image": "https://lh3.googleusercontent.com/d/18BemDPwA123WwMCubSsMoU2hPal00xXJ=s400?authuser=0",
  "time": "2025-08-08 08:32:06",
  "field": "e452d91c-3c05-4827-a190-9d0b39eb497d",
  "id": 446,
  "__v": 0
},
{
  "_id": {
    "$oid": "6895b6314bdb8afcd5386432"
  },
  "Aname": {
    "Name": "AGNES",
    "Mname": "",
    "Surname": "ODINAKA"
  },
  "State": "",
  "LocalGovernment": "",
  "Sex": "",
  "Bloodgroup": "",
  "PhoneNumber": "",
  "EmergencyNo": "",
  "RegNo": "M25/065",
  "Validity": "2025-2027",
  "picturepath": "image/21600.jpg",
  "imgurl": "https://drive.google.com/file/d/1GyYE0eUxlUMzBY1RsuUtbY1T1dsVtWhw/view?usp=drivesdk",
  "image": "https://lh3.googleusercontent.com/d/1GyYE0eUxlUMzBY1RsuUtbY1T1dsVtWhw=s400?authuser=0",
  "time": "2025-08-08 08:32:49",
  "field": "183dd4ef-734b-4ee5-bd28-c6b33399dff6",
  "id": 447,
  "__v": 0
},
{
  "_id": {
    "$oid": "6895b65f4bdb8afcd5386439"
  },
  "Aname": {
    "Name": "CONFIDENCE",
    "Mname": "",
    "Surname": "AMADI"
  },
  "State": "",
  "LocalGovernment": "",
  "Sex": "",
  "Bloodgroup": "",
  "PhoneNumber": "",
  "EmergencyNo": "",
  "RegNo": "M25/007",
  "Validity": "2025-2027",
  "picturepath": "image/39216.jpg",
  "imgurl": "https://drive.google.com/file/d/13vO7HgixfqfKGFXkM0IIkLwH078vswMx/view?usp=drivesdk",
  "image": "https://lh3.googleusercontent.com/d/13vO7HgixfqfKGFXkM0IIkLwH078vswMx=s400?authuser=0",
  "time": "2025-08-08 08:33:35",
  "field": "e1c54011-9f8e-452d-8331-42676c6016ca",
  "id": 448,
  "__v": 0
},
{
  "_id": {
    "$oid": "6895b68e4bdb8afcd5386440"
  },
  "Aname": {
    "Name": "GOODNESS",
    "Mname": "",
    "Surname": "ATTAH"
  },
  "State": "",
  "LocalGovernment": "",
  "Sex": "",
  "Bloodgroup": "",
  "PhoneNumber": "",
  "EmergencyNo": "",
  "RegNo": "M25/014",
  "Validity": "2025-2027",
  "picturepath": "image/98685.jpg",
  "imgurl": "https://drive.google.com/file/d/1lE6pcHSuPrwUMuVkdPnHZkv-zPIsvVU8/view?usp=drivesdk",
  "image": "https://lh3.googleusercontent.com/d/1lE6pcHSuPrwUMuVkdPnHZkv-zPIsvVU8=s400?authuser=0",
  "time": "2025-08-08 08:34:22",
  "field": "83ec4e7e-9f88-4559-8b98-46d524ae92de",
  "id": 449,
  "__v": 0
},
{
  "_id": {
    "$oid": "6895b6bf4bdb8afcd5386447"
  },
  "Aname": {
    "Name": "JOY",
    "Mname": "",
    "Surname": "IGWE"
  },
  "State": "",
  "LocalGovernment": "",
  "Sex": "",
  "Bloodgroup": "",
  "PhoneNumber": "",
  "EmergencyNo": "",
  "RegNo": "M25/042",
  "Validity": "2025-2027",
  "picturepath": "image/62662.jpg",
  "imgurl": "https://drive.google.com/file/d/1vEy08LNpPmqj4iB3ACR_2RLnsPvA1PNt/view?usp=drivesdk",
  "image": "https://lh3.googleusercontent.com/d/1vEy08LNpPmqj4iB3ACR_2RLnsPvA1PNt=s400?authuser=0",
  "time": "2025-08-08 08:35:11",
  "field": "d084a6fd-0257-4b6a-af43-ce1c41c5be4d",
  "id": 450,
  "__v": 0
},
{
  "_id": {
    "$oid": "6895b6f94bdb8afcd538644e"
  },
  "Aname": {
    "Name": "PRECIOUS",
    "Mname": "OGECHUKWU",
    "Surname": "NWACHUKWU"
  },
  "State": "",
  "LocalGovernment": "",
  "Sex": "",
  "Bloodgroup": "",
  "PhoneNumber": "",
  "EmergencyNo": "",
  "RegNo": "M24/064",
  "Validity": "2024-2026",
  "picturepath": "image/99065.jpg",
  "imgurl": "https://drive.google.com/file/d/1GuJhOTOXsp3XgaJ09B1jy49adJ5xkEhg/view?usp=drivesdk",
  "image": "https://lh3.googleusercontent.com/d/1GuJhOTOXsp3XgaJ09B1jy49adJ5xkEhg=s400?authuser=0",
  "time": "2025-08-08 08:36:09",
  "field": "e1546941-4c95-4992-8d00-3fbeef7e7387",
  "id": 451,
  "__v": 0
},
{
  "_id": {
    "$oid": "6895bd65a32cf6c1867ea580"
  },
  "Aname": {
    "Name": "EZINNE",
    "Mname": "FAVOUR",
    "Surname": "PPARA"
  },
  "State": "",
  "LocalGovernment": "",
  "Sex": "",
  "Bloodgroup": "",
  "PhoneNumber": "",
  "EmergencyNo": "",
  "RegNo": "M25/083",
  "Validity": "2025-2027",
  "picturepath": "image/34325.jpg",
  "imgurl": "https://drive.google.com/file/d/1BPQ0bj2QO6POyvjsrJEMCM8uu5cCEwLY/view?usp=drivesdk",
  "image": "https://lh3.googleusercontent.com/d/1BPQ0bj2QO6POyvjsrJEMCM8uu5cCEwLY=s400?authuser=0",
  "time": "2025-08-08 09:03:33",
  "field": "2278a6f2-330e-429d-976f-d32272854f86",
  "id": 452,
  "__v": 0
},
{
  "_id": {
    "$oid": "6895bda2a32cf6c1867ea587"
  },
  "Aname": {
    "Name": "LILIAN",
    "Mname": "",
    "Surname": "NNAGBORO"
  },
  "State": "",
  "LocalGovernment": "",
  "Sex": "",
  "Bloodgroup": "",
  "PhoneNumber": "",
  "EmergencyNo": "",
  "RegNo": "M25/057",
  "Validity": "2025-2027",
  "picturepath": "image/43180.jpg",
  "imgurl": "https://drive.google.com/file/d/1lwkcHkcse2B2oNFitNMKxrLf6obOAgj4/view?usp=drivesdk",
  "image": "https://lh3.googleusercontent.com/d/1lwkcHkcse2B2oNFitNMKxrLf6obOAgj4=s400?authuser=0",
  "time": "2025-08-08 09:04:34",
  "field": "0ca79aaa-3afc-4437-93a4-4212b71f8b88",
  "id": 453,
  "__v": 0
},
{
  "_id": {
    "$oid": "6895bddea32cf6c1867ea58e"
  },
  "Aname": {
    "Name": "ASSUMPTA",
    "Mname": "",
    "Surname": "DURU"
  },
  "State": "",
  "LocalGovernment": "",
  "Sex": "",
  "Bloodgroup": "",
  "PhoneNumber": "",
  "EmergencyNo": "",
  "RegNo": "M25/021",
  "Validity": "2025-2027",
  "picturepath": "image/66106.jpg",
  "imgurl": "https://drive.google.com/file/d/174mkKtgc5cUOfRyTemWlPcaiZQfHxkcy/view?usp=drivesdk",
  "image": "https://lh3.googleusercontent.com/d/174mkKtgc5cUOfRyTemWlPcaiZQfHxkcy=s400?authuser=0",
  "time": "2025-08-08 09:05:34",
  "field": "e63f3080-b6d6-4197-b10a-51279dc3d8bd",
  "id": 454,
  "__v": 0
},
{
  "_id": {
    "$oid": "6895bf4eb5bdd3069fda08dd"
  },
  "Aname": {
    "Name": "MIRABEL",
    "Mname": "",
    "Surname": "OKUEDO"
  },
  "State": "",
  "LocalGovernment": "",
  "Sex": "",
  "Bloodgroup": "",
  "PhoneNumber": "",
  "EmergencyNo": "",
  "RegNo": "M25/087",
  "Validity": "2025-2027",
  "picturepath": "image/24096.jpg",
  "imgurl": "https://drive.google.com/file/d/1QugnVrJLphn4bjupycoxB2i7LchzpAxv/view?usp=drivesdk",
  "image": "https://lh3.googleusercontent.com/d/1QugnVrJLphn4bjupycoxB2i7LchzpAxv=s400?authuser=0",
  "time": "2025-08-08 09:11:42",
  "field": "6cc81240-d6df-443f-a559-ec61bba53624",
  "id": 457,
  "__v": 0
},
{
  "_id": {
    "$oid": "6895bf96b5bdd3069fda08e4"
  },
  "Aname": {
    "Name": "CHIOMA",
    "Mname": "",
    "Surname": "DANIEL"
  },
  "State": "",
  "LocalGovernment": "",
  "Sex": "",
  "Bloodgroup": "",
  "PhoneNumber": "",
  "EmergencyNo": "",
  "RegNo": "M25/019",
  "Validity": "2025-2027",
  "picturepath": "image/51828.jpg",
  "imgurl": "https://drive.google.com/file/d/1KfHg8VRiszflJm30uOULIdOtnU6Nd85J/view?usp=drivesdk",
  "image": "https://lh3.googleusercontent.com/d/1KfHg8VRiszflJm30uOULIdOtnU6Nd85J=s400?authuser=0",
  "time": "2025-08-08 09:12:54",
  "field": "11aedec9-6f16-4d7b-8590-9690fffb03e5",
  "id": 458,
  "__v": 0
},
{
  "_id": {
    "$oid": "6895bfd2b5bdd3069fda08eb"
  },
  "Aname": {
    "Name": "GIFT",
    "Mname": "",
    "Surname": "MBAMARA"
  },
  "State": "",
  "LocalGovernment": "",
  "Sex": "",
  "Bloodgroup": "",
  "PhoneNumber": "",
  "EmergencyNo": "",
  "RegNo": "M25/050",
  "Validity": "2025-2027",
  "picturepath": "image/02995.jpg",
  "imgurl": "https://drive.google.com/file/d/1OcxHdQA2qhUx51_Naig7yADc5xKtCMIC/view?usp=drivesdk",
  "image": "https://lh3.googleusercontent.com/d/1OcxHdQA2qhUx51_Naig7yADc5xKtCMIC=s400?authuser=0",
  "time": "2025-08-08 09:13:54",
  "field": "4059028e-2b11-4d5e-9bf7-90fda32539bd",
  "id": 459,
  "__v": 0
},
{
  "_id": {
    "$oid": "6895c2feb5bdd3069fda0906"
  },
  "Aname": {
    "Name": "AMARACHI",
    "Mname": "",
    "Surname": "JOHN"
  },
  "State": "",
  "LocalGovernment": "",
  "Sex": "",
  "Bloodgroup": "",
  "PhoneNumber": "",
  "EmergencyNo": "",
  "RegNo": "M25/008",
  "Validity": "2025-2027",
  "picturepath": "image/99133.jpg",
  "imgurl": "https://drive.google.com/file/d/1Vln-4kWh9jtqPaGXJfS2mNx-QSYrCM9M/view?usp=drivesdk",
  "image": "https://lh3.googleusercontent.com/d/1Vln-4kWh9jtqPaGXJfS2mNx-QSYrCM9M=s400?authuser=0",
  "time": "2025-08-08 09:27:26",
  "field": "2bdde394-f979-4fbb-ae90-10f781b49717",
  "id": 462,
  "__v": 0
},
{
  "_id": {
    "$oid": "6895c3b8b5bdd3069fda0911"
  },
  "Aname": {
    "Name": "FAVOUR",
    "Mname": "AMARACHI",
    "Surname": "UZOMA"
  },
  "State": "",
  "LocalGovernment": "",
  "Sex": "",
  "Bloodgroup": "",
  "PhoneNumber": "",
  "EmergencyNo": "",
  "RegNo": "M25/097",
  "Validity": "2025-2027",
  "picturepath": "image/60109.jpg",
  "imgurl": "https://drive.google.com/file/d/1XDlKFSIEL9YTN6_6nOKR1Sp4SD9Sz64E/view?usp=drivesdk",
  "image": "https://lh3.googleusercontent.com/d/1XDlKFSIEL9YTN6_6nOKR1Sp4SD9Sz64E=s400?authuser=0",
  "time": "2025-08-08 09:30:32",
  "field": "fd9daa2d-f1f0-48b5-bc28-2cbae50fd2bb",
  "id": 463,
  "__v": 0
},
{
  "_id": {
    "$oid": "6895c3f8b5bdd3069fda0918"
  },
  "Aname": {
    "Name": "MIRACLE",
    "Mname": "",
    "Surname": "ODUKWU"
  },
  "State": "",
  "LocalGovernment": "",
  "Sex": "",
  "Bloodgroup": "",
  "PhoneNumber": "",
  "EmergencyNo": "",
  "RegNo": "M25/066",
  "Validity": "2025-2027",
  "picturepath": "image/91108.jpg",
  "imgurl": "https://drive.google.com/file/d/1-2ogl9qekrjRjDwGTYXUgCO6j-6it6Hk/view?usp=drivesdk",
  "image": "https://lh3.googleusercontent.com/d/1-2ogl9qekrjRjDwGTYXUgCO6j-6it6Hk=s400?authuser=0",
  "time": "2025-08-08 09:31:36",
  "field": "ee04385e-a5d7-41f6-b46e-0f90b0754357",
  "id": 464,
  "__v": 0
},
{
  "_id": {
    "$oid": "6895c430b5bdd3069fda091f"
  },
  "Aname": {
    "Name": "OLUEBUBE",
    "Mname": "",
    "Surname": "EZE"
  },
  "State": "",
  "LocalGovernment": "",
  "Sex": "",
  "Bloodgroup": "",
  "PhoneNumber": "",
  "EmergencyNo": "",
  "RegNo": "M25/035",
  "Validity": "2025-2027",
  "picturepath": "image/58312.jpg",
  "imgurl": "https://drive.google.com/file/d/1HKVOPeNS5Sv1HYR3MWcEjW7bAapPwcPG/view?usp=drivesdk",
  "image": "https://lh3.googleusercontent.com/d/1HKVOPeNS5Sv1HYR3MWcEjW7bAapPwcPG=s400?authuser=0",
  "time": "2025-08-08 09:32:32",
  "field": "f7301491-d088-4138-8faf-96453689960b",
  "id": 465,
  "__v": 0
},
{
  "_id": {
    "$oid": "6895c46bb5bdd3069fda0926"
  },
  "Aname": {
    "Name": "PRAISE",
    "Mname": "CHIMDIYA",
    "Surname": "UGOCHUKWU"
  },
  "State": "",
  "LocalGovernment": "",
  "Sex": "",
  "Bloodgroup": "",
  "PhoneNumber": "",
  "EmergencyNo": "",
  "RegNo": "M25/092",
  "Validity": "2025-2027",
  "picturepath": "image/33054.jpg",
  "imgurl": "https://drive.google.com/file/d/1KxiUJE93fAE2-Nk94tT9mw3fAqNF4pMK/view?usp=drivesdk",
  "image": "https://lh3.googleusercontent.com/d/1KxiUJE93fAE2-Nk94tT9mw3fAqNF4pMK=s400?authuser=0",
  "time": "2025-08-08 09:33:31",
  "field": "33de42f7-08f2-457d-9c0f-b5cae8312173",
  "id": 466,
  "__v": 0
},
{
  "_id": {
    "$oid": "6895c4a2b5bdd3069fda092d"
  },
  "Aname": {
    "Name": "ESTHER",
    "Mname": "OLUEBUBE",
    "Surname": "OPARA"
  },
  "State": "",
  "LocalGovernment": "",
  "Sex": "",
  "Bloodgroup": "",
  "PhoneNumber": "",
  "EmergencyNo": "",
  "RegNo": "M25/085",
  "Validity": "2025-2027",
  "picturepath": "image/21242.jpg",
  "imgurl": "https://drive.google.com/file/d/1jWmMbkR2Z_13mTaq0C9CbXRuBMTFvrdS/view?usp=drivesdk",
  "image": "https://lh3.googleusercontent.com/d/1jWmMbkR2Z_13mTaq0C9CbXRuBMTFvrdS=s400?authuser=0",
  "time": "2025-08-08 09:34:26",
  "field": "1d0dd2a5-adc8-4082-af94-2f9a80d33e3b",
  "id": 467,
  "__v": 0
},
{
  "_id": {
    "$oid": "6895c4e4b5bdd3069fda0934"
  },
  "Aname": {
    "Name": "RUTH",
    "Mname": "ULPAI",
    "Surname": "OKORO"
  },
  "State": "",
  "LocalGovernment": "",
  "Sex": "",
  "Bloodgroup": "",
  "PhoneNumber": "",
  "EmergencyNo": "",
  "RegNo": "M25/075",
  "Validity": "2025-2027",
  "picturepath": "image/20242.jpg",
  "imgurl": "https://drive.google.com/file/d/1IeNjKM8CROa3IOYYLLuYl9W1d39MaRo_/view?usp=drivesdk",
  "image": "https://lh3.googleusercontent.com/d/1IeNjKM8CROa3IOYYLLuYl9W1d39MaRo_=s400?authuser=0",
  "time": "2025-08-08 09:35:32",
  "field": "f5d13e6e-7c48-469f-ba1f-3828b09f51aa",
  "id": 468,
  "__v": 0
},
{
  "_id": {
    "$oid": "6895c532b5bdd3069fda093b"
  },
  "Aname": {
    "Name": "QUEEN",
    "Mname": "",
    "Surname": "METU"
  },
  "State": "",
  "LocalGovernment": "",
  "Sex": "",
  "Bloodgroup": "",
  "PhoneNumber": "",
  "EmergencyNo": "",
  "RegNo": "M25/051",
  "Validity": "2025-2027",
  "picturepath": "image/24380.jpg",
  "imgurl": "https://drive.google.com/file/d/1pkDuceJLVoFXpdWJ7KyOy6eAXEHIlHqu/view?usp=drivesdk",
  "image": "https://lh3.googleusercontent.com/d/1pkDuceJLVoFXpdWJ7KyOy6eAXEHIlHqu=s400?authuser=0",
  "time": "2025-08-08 09:36:50",
  "field": "2bfe6ce4-726a-40d5-9a7c-57af1334aa3f",
  "id": 469,
  "__v": 0
},
{
  "_id": {
    "$oid": "6895c6f89af344ccf9c75c67"
  },
  "Aname": {
    "Name": "CYNTHIA",
    "Mname": "",
    "Surname": "EZEIFEDIBA"
  },
  "State": "",
  "LocalGovernment": "",
  "Sex": "",
  "Bloodgroup": "",
  "PhoneNumber": "",
  "EmergencyNo": "",
  "RegNo": "M25/037",
  "Validity": "2025-2027",
  "picturepath": "image/96920.jpg",
  "imgurl": "https://drive.google.com/file/d/1I2-10TirIiQVN7zB-F5N18woBhgK5-VG/view?usp=drivesdk",
  "image": "https://lh3.googleusercontent.com/d/1I2-10TirIiQVN7zB-F5N18woBhgK5-VG=s400?authuser=0",
  "time": "2025-08-08 09:44:24",
  "field": "8abf198a-61c3-48f7-8faf-f131352ff211",
  "id": 471,
  "__v": 0
},
{
  "_id": {
    "$oid": "6895c8779af344ccf9c75c6e"
  },
  "Aname": {
    "Name": "PRISCA",
    "Mname": "CHIBUZOR",
    "Surname": "NNEJI"
  },
  "State": "",
  "LocalGovernment": "",
  "Sex": "",
  "Bloodgroup": "",
  "PhoneNumber": "",
  "EmergencyNo": "",
  "RegNo": "M25/058",
  "Validity": "2025-2027",
  "picturepath": "image/39295.jpg",
  "imgurl": "https://drive.google.com/file/d/1HQ5RHigziBuE-kUyhnoTGIEcUiHQKv1P/view?usp=drivesdk",
  "image": "https://lh3.googleusercontent.com/d/1HQ5RHigziBuE-kUyhnoTGIEcUiHQKv1P=s400?authuser=0",
  "time": "2025-08-08 09:50:47",
  "field": "662c2f75-162d-44ec-87fb-1cd7fad22c48",
  "id": 472,
  "__v": 0
},
{
  "_id": {
    "$oid": "6895c8b69af344ccf9c75c75"
  },
  "Aname": {
    "Name": "ANASTECIA",
    "Mname": "ONYIN",
    "Surname": "EMMANUEL"
  },
  "State": "",
  "LocalGovernment": "",
  "Sex": "",
  "Bloodgroup": "",
  "PhoneNumber": "",
  "EmergencyNo": "",
  "RegNo": "M25/032",
  "Validity": "2025-2027",
  "picturepath": "image/80840.jpg",
  "imgurl": "https://drive.google.com/file/d/1DogKyRBhBfBISzizw_o7RkLAC79COYX6/view?usp=drivesdk",
  "image": "https://lh3.googleusercontent.com/d/1DogKyRBhBfBISzizw_o7RkLAC79COYX6=s400?authuser=0",
  "time": "2025-08-08 09:51:50",
  "field": "58c2b4c2-6c57-458b-896d-6c89b5975023",
  "id": 473,
  "__v": 0
},
{
  "_id": {
    "$oid": "6895c8fe9af344ccf9c75c7c"
  },
  "Aname": {
    "Name": "CHIGAEMEZU",
    "Mname": "",
    "Surname": "EKEH"
  },
  "State": "",
  "LocalGovernment": "",
  "Sex": "F",
  "Bloodgroup": "",
  "PhoneNumber": "",
  "EmergencyNo": "",
  "RegNo": "M25/026",
  "Validity": "2025-2027",
  "picturepath": "image/09262.jpg",
  "imgurl": "https://drive.google.com/file/d/1F1Dovl-my-zgUuPyr6UPQvAxabOzOKNB/view?usp=drivesdk",
  "image": "https://lh3.googleusercontent.com/d/1F1Dovl-my-zgUuPyr6UPQvAxabOzOKNB=s400?authuser=0",
  "time": "2025-08-08 09:53:02",
  "field": "278b4b8d-1a02-49d7-bc22-04bf93a103b5",
  "id": 474,
  "__v": 0
},
{
  "_id": {
    "$oid": "6895c9569af344ccf9c75c83"
  },
  "Aname": {
    "Name": "DANIELLA",
    "Mname": "",
    "Surname": "EMMANUEL"
  },
  "State": "",
  "LocalGovernment": "",
  "Sex": "",
  "Bloodgroup": "",
  "PhoneNumber": "",
  "EmergencyNo": "",
  "RegNo": "M25/033",
  "Validity": "2025-2027",
  "picturepath": "image/84229.jpg",
  "imgurl": "https://drive.google.com/file/d/1Kan8rNLJxuBtCx5nBesAweJb1BzCXbzs/view?usp=drivesdk",
  "image": "https://lh3.googleusercontent.com/d/1Kan8rNLJxuBtCx5nBesAweJb1BzCXbzs=s400?authuser=0",
  "time": "2025-08-08 09:54:30",
  "field": "fa348eed-0067-4467-b547-8d9f688fa4b8",
  "id": 475,
  "__v": 0
},
{
  "_id": {
    "$oid": "6895c9ae9af344ccf9c75c8a"
  },
  "Aname": {
    "Name": "NNEOMA",
    "Mname": "DESTINY",
    "Surname": "UKANACHO"
  },
  "State": "",
  "LocalGovernment": "",
  "Sex": "",
  "Bloodgroup": "",
  "PhoneNumber": "",
  "EmergencyNo": "",
  "RegNo": "M25/094",
  "Validity": "2025-2027",
  "picturepath": "image/46882.jpg",
  "imgurl": "https://drive.google.com/file/d/1DOJx-r4LR3vEYe3UPI_QEj3d_nyl_Qz3/view?usp=drivesdk",
  "image": "https://lh3.googleusercontent.com/d/1DOJx-r4LR3vEYe3UPI_QEj3d_nyl_Qz3=s400?authuser=0",
  "time": "2025-08-08 09:55:58",
  "field": "7e6c720c-8ceb-4bd5-805b-55e9e11fd449",
  "id": 476,
  "__v": 0
},
{
  "_id": {
    "$oid": "6895cab29af344ccf9c75c91"
  },
  "Aname": {
    "Name": "CHIDIMMA",
    "Mname": "",
    "Surname": "NNADI"
  },
  "State": "",
  "LocalGovernment": "",
  "Sex": "",
  "Bloodgroup": "",
  "PhoneNumber": "",
  "EmergencyNo": "",
  "RegNo": "M24/071",
  "Validity": "2024-2026",
  "picturepath": "image/08402.jpg",
  "imgurl": "https://drive.google.com/file/d/1n6H979LjwTh30XKUqUQzxHLOCybZ8B9y/view?usp=drivesdk",
  "image": "https://lh3.googleusercontent.com/d/1n6H979LjwTh30XKUqUQzxHLOCybZ8B9y=s400?authuser=0",
  "time": "2025-08-08 10:00:18",
  "field": "7567858d-7650-4ffc-be0c-a4da42573921",
  "id": 477,
  "__v": 0
},
{
  "_id": {
    "$oid": "6895cb3b9af344ccf9c75c9a"
  },
  "Aname": {
    "Name": "CHIAMAKA",
    "Mname": "",
    "Surname": "CALLISTUS"
  },
  "State": "",
  "LocalGovernment": "",
  "Sex": "",
  "Bloodgroup": "",
  "PhoneNumber": "",
  "EmergencyNo": "",
  "RegNo": "M24/014",
  "Validity": "2024-2026",
  "picturepath": "image/45112.jpg",
  "imgurl": "https://drive.google.com/file/d/156s6pYGbB7680LPC3-dAxkzWvmGozK0I/view?usp=drivesdk",
  "image": "https://lh3.googleusercontent.com/d/156s6pYGbB7680LPC3-dAxkzWvmGozK0I=s400?authuser=0",
  "time": "2025-08-08 10:02:35",
  "field": "a04abcb0-3e0c-45ba-a946-04ad9b1f625a",
  "id": 478,
  "__v": 0
},
{
  "_id": {
    "$oid": "6895cba39af344ccf9c75ca1"
  },
  "Aname": {
    "Name": "GIFT",
    "Mname": "",
    "Surname": "ILO"
  },
  "State": "",
  "LocalGovernment": "",
  "Sex": "",
  "Bloodgroup": "",
  "PhoneNumber": "",
  "EmergencyNo": "",
  "RegNo": "M24/053",
  "Validity": "2024-2026",
  "picturepath": "image/80523.jpg",
  "imgurl": "https://drive.google.com/file/d/18UliZB_Xxk02YxCJahmztgzOOdz8lthy/view?usp=drivesdk",
  "image": "https://lh3.googleusercontent.com/d/18UliZB_Xxk02YxCJahmztgzOOdz8lthy=s400?authuser=0",
  "time": "2025-08-08 10:04:19",
  "field": "982d11c1-ef49-4530-b9b9-eec08342748d",
  "id": 479,
  "__v": 0
},
{
  "_id": {
    "$oid": "6895cbe39af344ccf9c75ca8"
  },
  "Aname": {
    "Name": "NANCY",
    "Mname": "ONYONTECHI",
    "Surname": "OLIUUS"
  },
  "State": "",
  "LocalGovernment": "",
  "Sex": "",
  "Bloodgroup": "",
  "PhoneNumber": "",
  "EmergencyNo": "",
  "RegNo": "M25/017",
  "Validity": "2024-2026",
  "picturepath": "image/60684.jpg",
  "imgurl": "https://drive.google.com/file/d/1ZRxGP3cwdpSBBEPx0TQXhPpQjIqLXgi9/view?usp=drivesdk",
  "image": "https://lh3.googleusercontent.com/d/1ZRxGP3cwdpSBBEPx0TQXhPpQjIqLXgi9=s400?authuser=0",
  "time": "2025-08-08 10:05:23",
  "field": "63eb2a93-9e17-4b43-bb81-76d2622199ac",
  "id": 480,
  "__v": 0
},
{
  "_id": {
    "$oid": "6895cc469af344ccf9c75cb1"
  },
  "Aname": {
    "Name": "CHIDIMMA",
    "Mname": "",
    "Surname": "NWOSU"
  },
  "State": "",
  "LocalGovernment": "",
  "Sex": "",
  "Bloodgroup": "",
  "PhoneNumber": "",
  "EmergencyNo": "",
  "RegNo": "M24/076",
  "Validity": "2024-2026",
  "picturepath": "image/18089.jpg",
  "imgurl": "https://drive.google.com/file/d/1qtNmDrGzxR_akA_5jGD-JBY3IRuKcq2C/view?usp=drivesdk",
  "image": "https://lh3.googleusercontent.com/d/1qtNmDrGzxR_akA_5jGD-JBY3IRuKcq2C=s400?authuser=0",
  "time": "2025-08-08 10:07:02",
  "field": "1fa69f7b-d227-434d-b150-a2e086f64ad6",
  "id": 481,
  "__v": 0
},
{
  "_id": {
    "$oid": "6895cc819af344ccf9c75cb8"
  },
  "Aname": {
    "Name": "CHINENYE",
    "Mname": "FAVOUR",
    "Surname": "OKECHUKWU"
  },
  "State": "",
  "LocalGovernment": "",
  "Sex": "",
  "Bloodgroup": "",
  "PhoneNumber": "",
  "EmergencyNo": "",
  "RegNo": "M25/090",
  "Validity": "2024-2026",
  "picturepath": "image/48015.jpg",
  "imgurl": "https://drive.google.com/file/d/1KWXhwCxrdB2RQ6qDS2ZOaoW3lTa6TXJD/view?usp=drivesdk",
  "image": "https://lh3.googleusercontent.com/d/1KWXhwCxrdB2RQ6qDS2ZOaoW3lTa6TXJD=s400?authuser=0",
  "time": "2025-08-08 10:08:01",
  "field": "0e499da8-ce6d-461c-bb2a-196c1bac452e",
  "id": 482,
  "__v": 0
},
{
  "_id": {
    "$oid": "6895ccb69af344ccf9c75cbf"
  },
  "Aname": {
    "Name": "CHIAMAKA",
    "Mname": "JULIET",
    "Surname": "CHRISTOPHER"
  },
  "State": "",
  "LocalGovernment": "",
  "Sex": "",
  "Bloodgroup": "",
  "PhoneNumber": "",
  "EmergencyNo": "",
  "RegNo": "M24/075",
  "Validity": "2024-2026",
  "picturepath": "image/64383.jpg",
  "imgurl": "https://drive.google.com/file/d/1-uVyEqcHy1O982BlQzGgyiTsp79I0g0t/view?usp=drivesdk",
  "image": "https://lh3.googleusercontent.com/d/1-uVyEqcHy1O982BlQzGgyiTsp79I0g0t=s400?authuser=0",
  "time": "2025-08-08 10:08:54",
  "field": "137fda5a-a274-4ce9-b1ae-36683849bd08",
  "id": 483,
  "__v": 0
},
{
  "_id": {
    "$oid": "6895cce69af344ccf9c75cc6"
  },
  "Aname": {
    "Name": "CHINWE",
    "Mname": "",
    "Surname": "OPARA"
  },
  "State": "",
  "LocalGovernment": "",
  "Sex": "",
  "Bloodgroup": "",
  "PhoneNumber": "",
  "EmergencyNo": "",
  "RegNo": "M25/",
  "Validity": "2024-2026",
  "picturepath": "image/58530.jpg",
  "imgurl": "https://drive.google.com/file/d/18YM_J_HnYnTErLQmQTQ28xe-MOCU8bLX/view?usp=drivesdk",
  "image": "https://lh3.googleusercontent.com/d/18YM_J_HnYnTErLQmQTQ28xe-MOCU8bLX=s400?authuser=0",
  "time": "2025-08-08 10:09:42",
  "field": "b156fe08-46d5-485f-af29-79b5ff8bfff5",
  "id": 484,
  "__v": 0
},
{
  "_id": {
    "$oid": "6895cd239af344ccf9c75ccd"
  },
  "Aname": {
    "Name": "DORIS",
    "Mname": "",
    "Surname": "BONIFACE"
  },
  "State": "",
  "LocalGovernment": "",
  "Sex": "",
  "Bloodgroup": "",
  "PhoneNumber": "",
  "EmergencyNo": "",
  "RegNo": "M24/009",
  "Validity": "2024-2026",
  "picturepath": "image/25328.jpg",
  "imgurl": "https://drive.google.com/file/d/1GFYLZVNoCI9V9NeTaLA1Rcz92mbJ2Bk_/view?usp=drivesdk",
  "image": "https://lh3.googleusercontent.com/d/1GFYLZVNoCI9V9NeTaLA1Rcz92mbJ2Bk_=s400?authuser=0",
  "time": "2025-08-08 10:10:43",
  "field": "afe89319-3b29-46a7-9ea9-1caf5a36d7b0",
  "id": 485,
  "__v": 0
},
{
  "_id": {
    "$oid": "6895cd619af344ccf9c75cd4"
  },
  "Aname": {
    "Name": "ONYONYE",
    "Mname": "MARVELLOUS",
    "Surname": "OZO-ILO"
  },
  "State": "",
  "LocalGovernment": "",
  "Sex": "",
  "Bloodgroup": "",
  "PhoneNumber": "",
  "EmergencyNo": "",
  "RegNo": "M24/",
  "Validity": "2024-2026",
  "picturepath": "image/50048.jpg",
  "imgurl": "https://drive.google.com/file/d/1FfZB365iP08BSYcQR5L1nKzltIOPaX_M/view?usp=drivesdk",
  "image": "https://lh3.googleusercontent.com/d/1FfZB365iP08BSYcQR5L1nKzltIOPaX_M=s400?authuser=0",
  "time": "2025-08-08 10:11:45",
  "field": "d183de42-3013-4199-bf59-1c2d884b2a0f",
  "id": 486,
  "__v": 0
},
{
  "_id": {
    "$oid": "6895ce429af344ccf9c75cdf"
  },
  "Aname": {
    "Name": "CHEKWUBE",
    "Mname": "HOPE",
    "Surname": "OKIA"
  },
  "State": "",
  "LocalGovernment": "",
  "Sex": "",
  "Bloodgroup": "",
  "PhoneNumber": "",
  "EmergencyNo": "",
  "RegNo": "J24/093",
  "Validity": "2024-2026",
  "picturepath": "image/26259.jpg",
  "imgurl": "https://drive.google.com/file/d/1Np35K2RLuAlMmTKSxhgUh5IugeZsVW33/view?usp=drivesdk",
  "image": "https://lh3.googleusercontent.com/d/1Np35K2RLuAlMmTKSxhgUh5IugeZsVW33=s400?authuser=0",
  "time": "2025-08-08 10:15:30",
  "field": "c04d0b05-ec93-4102-b87b-eb212a65592a",
  "id": 487,
  "__v": 0
},
{
  "_id": {
    "$oid": "6895ce959af344ccf9c75ce6"
  },
  "Aname": {
    "Name": "LILIAN",
    "Mname": "CHIDINMA",
    "Surname": "OGOR"
  },
  "State": "",
  "LocalGovernment": "",
  "Sex": "",
  "Bloodgroup": "",
  "PhoneNumber": "",
  "EmergencyNo": "",
  "RegNo": "M24/087",
  "Validity": "2024-2026",
  "picturepath": "image/12661.jpg",
  "imgurl": "https://drive.google.com/file/d/1Jk-AK8UFt6hWaQV8Z4rFihKx5Yi3GU2r/view?usp=drivesdk",
  "image": "https://lh3.googleusercontent.com/d/1Jk-AK8UFt6hWaQV8Z4rFihKx5Yi3GU2r=s400?authuser=0",
  "time": "2025-08-08 10:16:53",
  "field": "06adf4ac-493a-4611-8fe4-0efb2e7928ed",
  "id": 488,
  "__v": 0
},
{
  "_id": {
    "$oid": "6895cec99af344ccf9c75ced"
  },
  "Aname": {
    "Name": "CONFIDENCE",
    "Mname": "",
    "Surname": "WILLIAMS"
  },
  "State": "",
  "LocalGovernment": "",
  "Sex": "",
  "Bloodgroup": "",
  "PhoneNumber": "",
  "EmergencyNo": "",
  "RegNo": "M24/115",
  "Validity": "2024-2026",
  "picturepath": "image/53316.jpg",
  "imgurl": "https://drive.google.com/file/d/17dncH730bv80_OzP74e8CyWCLRT0l9KZ/view?usp=drivesdk",
  "image": "https://lh3.googleusercontent.com/d/17dncH730bv80_OzP74e8CyWCLRT0l9KZ=s400?authuser=0",
  "time": "2025-08-08 10:17:45",
  "field": "4dc4600e-9c3d-49e2-8449-ff004031e6cb",
  "id": 489,
  "__v": 0
},
{
  "_id": {
    "$oid": "6895ceff9af344ccf9c75cf4"
  },
  "Aname": {
    "Name": "JOY",
    "Mname": "SUNDAY",
    "Surname": "UBA"
  },
  "State": "",
  "LocalGovernment": "",
  "Sex": "",
  "Bloodgroup": "",
  "PhoneNumber": "",
  "EmergencyNo": "",
  "RegNo": "M24/107",
  "Validity": "2024-2026",
  "picturepath": "image/95826.jpg",
  "imgurl": "https://drive.google.com/file/d/1uKgGOwWD1Inr7WGuej83SFfDjJyA61pD/view?usp=drivesdk",
  "image": "https://lh3.googleusercontent.com/d/1uKgGOwWD1Inr7WGuej83SFfDjJyA61pD=s400?authuser=0",
  "time": "2025-08-08 10:18:39",
  "field": "8da86018-f876-40c6-8aaa-3c5fc83c9344",
  "id": 490,
  "__v": 0
},
{
  "_id": {
    "$oid": "6895d10a9af344ccf9c75cfb"
  },
  "Aname": {
    "Name": "FAVOUR",
    "Mname": "",
    "Surname": "OLUEBUBE"
  },
  "State": "",
  "LocalGovernment": "",
  "Sex": "",
  "Bloodgroup": "",
  "PhoneNumber": "",
  "EmergencyNo": "",
  "RegNo": "M24/040",
  "Validity": "2024-2026",
  "picturepath": "image/10080.jpg",
  "imgurl": "https://drive.google.com/file/d/1-Xk9eGUdSVAdwtDRdQ5xhF5gRQzHlQPT/view?usp=drivesdk",
  "image": "https://lh3.googleusercontent.com/d/1-Xk9eGUdSVAdwtDRdQ5xhF5gRQzHlQPT=s400?authuser=0",
  "time": "2025-08-08 10:27:22",
  "field": "2a3c2c2c-b7ff-4229-bfb0-d908d129b99c",
  "id": 491,
  "__v": 0
},
{
  "_id": {
    "$oid": "6895d1459af344ccf9c75d02"
  },
  "Aname": {
    "Name": "VICTORY",
    "Mname": "",
    "Surname": "CHARLSE"
  },
  "State": "",
  "LocalGovernment": "",
  "Sex": "",
  "Bloodgroup": "",
  "PhoneNumber": "",
  "EmergencyNo": "",
  "RegNo": "M24/010",
  "Validity": "2024-2026",
  "picturepath": "image/69949.jpg",
  "imgurl": "https://drive.google.com/file/d/1GLL8GuFvwpUxfhw5O-R_HeKEj85NqSL-/view?usp=drivesdk",
  "image": "https://lh3.googleusercontent.com/d/1GLL8GuFvwpUxfhw5O-R_HeKEj85NqSL-=s400?authuser=0",
  "time": "2025-08-08 10:28:21",
  "field": "42b69b03-0547-4811-9952-102705d45ab0",
  "id": 492,
  "__v": 0
},
{
  "_id": {
    "$oid": "6895d17d9af344ccf9c75d09"
  },
  "Aname": {
    "Name": "AMARACHI",
    "Mname": "SARAH",
    "Surname": "OHAGURU"
  },
  "State": "",
  "LocalGovernment": "",
  "Sex": "",
  "Bloodgroup": "",
  "PhoneNumber": "",
  "EmergencyNo": "",
  "RegNo": "M24/088",
  "Validity": "2024-2026",
  "picturepath": "image/29216.jpg",
  "imgurl": "https://drive.google.com/file/d/1CC54oRAHobuOjovtnnRiu6dXw-70PD8b/view?usp=drivesdk",
  "image": "https://lh3.googleusercontent.com/d/1CC54oRAHobuOjovtnnRiu6dXw-70PD8b=s400?authuser=0",
  "time": "2025-08-08 10:29:17",
  "field": "f920057f-065e-4606-8445-ac73a3ac714f",
  "id": 493,
  "__v": 0
},
{
  "_id": {
    "$oid": "6895d1b79af344ccf9c75d10"
  },
  "Aname": {
    "Name": "OBUM",
    "Mname": "JENNIFER",
    "Surname": "UDECHUKWU"
  },
  "State": "",
  "LocalGovernment": "",
  "Sex": "",
  "Bloodgroup": "",
  "PhoneNumber": "",
  "EmergencyNo": "",
  "RegNo": "S24/114",
  "Validity": "2024-2026",
  "picturepath": "image/36593.jpg",
  "imgurl": "https://drive.google.com/file/d/1CkRyqqKufiN3yjzFOi43AKGW4K6tvz9O/view?usp=drivesdk",
  "image": "https://lh3.googleusercontent.com/d/1CkRyqqKufiN3yjzFOi43AKGW4K6tvz9O=s400?authuser=0",
  "time": "2025-08-08 10:30:15",
  "field": "0f925b6f-4c52-4003-8a3f-5d50e92336ee",
  "id": 494,
  "__v": 0
},
{
  "_id": {
    "$oid": "6895d1fc9af344ccf9c75d17"
  },
  "Aname": {
    "Name": "PRECIOUS",
    "Mname": "",
    "Surname": "AMAEFULA"
  },
  "State": "",
  "LocalGovernment": "",
  "Sex": "",
  "Bloodgroup": "",
  "PhoneNumber": "",
  "EmergencyNo": "",
  "RegNo": "M23/009",
  "Validity": "2023-2025",
  "picturepath": "image/41861.jpg",
  "imgurl": "https://drive.google.com/file/d/1JWjxVQtcGPiwibTFUYBbuuLF0sU8qZEn/view?usp=drivesdk",
  "image": "https://lh3.googleusercontent.com/d/1JWjxVQtcGPiwibTFUYBbuuLF0sU8qZEn=s400?authuser=0",
  "time": "2025-08-08 10:31:24",
  "field": "3ed3996c-63d2-4ebc-94f9-dc7a66a0e679",
  "id": 495,
  "__v": 0
},
{
  "_id": {
    "$oid": "6895d2379af344ccf9c75d1e"
  },
  "Aname": {
    "Name": "UCHECHI",
    "Mname": "ESTHER",
    "Surname": "MBALAWEM"
  },
  "State": "",
  "LocalGovernment": "",
  "Sex": "",
  "Bloodgroup": "",
  "PhoneNumber": "",
  "EmergencyNo": "",
  "RegNo": "S24/064",
  "Validity": "2024-2026",
  "picturepath": "image/13345.jpg",
  "imgurl": "https://drive.google.com/file/d/1-_ZN7t6Jwojjyz-CmYugBW7z14fLLt-1/view?usp=drivesdk",
  "image": "https://lh3.googleusercontent.com/d/1-_ZN7t6Jwojjyz-CmYugBW7z14fLLt-1=s400?authuser=0",
  "time": "2025-08-08 10:32:23",
  "field": "8181f1a6-fd37-4bd3-9b92-11d6041c398e",
  "id": 496,
  "__v": 0
},
{
  "_id": {
    "$oid": "6895d2689af344ccf9c75d25"
  },
  "Aname": {
    "Name": "CHINYERE",
    "Mname": "",
    "Surname": "FRIDAY"
  },
  "State": "",
  "LocalGovernment": "",
  "Sex": "",
  "Bloodgroup": "",
  "PhoneNumber": "",
  "EmergencyNo": "",
  "RegNo": "M24/038",
  "Validity": "2024-2026",
  "picturepath": "image/50245.jpg",
  "imgurl": "https://drive.google.com/file/d/1yFEF7L3_l6HtkNmNLaIlJDlUkknjY7bc/view?usp=drivesdk",
  "image": "https://lh3.googleusercontent.com/d/1yFEF7L3_l6HtkNmNLaIlJDlUkknjY7bc=s400?authuser=0",
  "time": "2025-08-08 10:33:12",
  "field": "9e362f60-c52b-4ad3-96fd-bf7dec940e71",
  "id": 497,
  "__v": 0
},
{
  "_id": {
    "$oid": "6895d2a39af344ccf9c75d2c"
  },
  "Aname": {
    "Name": "CHIAMAKA",
    "Mname": "JUDITH",
    "Surname": "OKECHUKWU"
  },
  "State": "",
  "LocalGovernment": "",
  "Sex": "",
  "Bloodgroup": "",
  "PhoneNumber": "",
  "EmergencyNo": "",
  "RegNo": "S24/090",
  "Validity": "2024-2026",
  "picturepath": "image/99822.jpg",
  "imgurl": "https://drive.google.com/file/d/1RgKoB2kXsjB8TEtvt5WAD4wJO2KDGJx6/view?usp=drivesdk",
  "image": "https://lh3.googleusercontent.com/d/1RgKoB2kXsjB8TEtvt5WAD4wJO2KDGJx6=s400?authuser=0",
  "time": "2025-08-08 10:34:11",
  "field": "2ead2f1a-9e88-4a3e-b29b-b3218b6b3084",
  "id": 498,
  "__v": 0
},
{
  "_id": {
    "$oid": "6895d2d69af344ccf9c75d33"
  },
  "Aname": {
    "Name": "CHINAGOROM",
    "Mname": "RE HEAL",
    "Surname": "OSUAGWU"
  },
  "State": "",
  "LocalGovernment": "",
  "Sex": "",
  "Bloodgroup": "",
  "PhoneNumber": "",
  "EmergencyNo": "",
  "RegNo": "M24/104",
  "Validity": "2024-2026",
  "picturepath": "image/29548.jpg",
  "imgurl": "https://drive.google.com/file/d/1txR1C7sAsfOqHERDI_BC_rl3i4ETh1fn/view?usp=drivesdk",
  "image": "https://lh3.googleusercontent.com/d/1txR1C7sAsfOqHERDI_BC_rl3i4ETh1fn=s400?authuser=0",
  "time": "2025-08-08 10:35:02",
  "field": "28013a73-82a2-49d3-a636-65e4acd5dbe2",
  "id": 499,
  "__v": 0
},
{
  "_id": {
    "$oid": "6895d30d9af344ccf9c75d3a"
  },
  "Aname": {
    "Name": "CHIDERA",
    "Mname": "S",
    "Surname": "JONAH"
  },
  "State": "",
  "LocalGovernment": "",
  "Sex": "",
  "Bloodgroup": "",
  "PhoneNumber": "",
  "EmergencyNo": "",
  "RegNo": "M24/008",
  "Validity": "2024-2026",
  "picturepath": "image/12415.jpg",
  "imgurl": "https://drive.google.com/file/d/1Oy29O7FCcgOYsJekEeyHuTkYWannoNFO/view?usp=drivesdk",
  "image": "https://lh3.googleusercontent.com/d/1Oy29O7FCcgOYsJekEeyHuTkYWannoNFO=s400?authuser=0",
  "time": "2025-08-08 10:35:57",
  "field": "a970d03a-c5a7-410a-8ffa-f10d410e23b6",
  "id": 500,
  "__v": 0
},
{
  "_id": {
    "$oid": "6895d33c9af344ccf9c75d41"
  },
  "Aname": {
    "Name": "JULIET",
    "Mname": "",
    "Surname": "OKECHUKWU"
  },
  "State": "",
  "LocalGovernment": "",
  "Sex": "",
  "Bloodgroup": "",
  "PhoneNumber": "",
  "EmergencyNo": "",
  "RegNo": "J24/091",
  "Validity": "2024-2026",
  "picturepath": "image/08890.jpg",
  "imgurl": "https://drive.google.com/file/d/1BPDNosgRWortauF_8JegykFHB1KT1AAu/view?usp=drivesdk",
  "image": "https://lh3.googleusercontent.com/d/1BPDNosgRWortauF_8JegykFHB1KT1AAu=s400?authuser=0",
  "time": "2025-08-08 10:36:44",
  "field": "44c15ab5-932a-44f5-9081-77bafdc22fd1",
  "id": 501,
  "__v": 0
},
{
  "_id": {
    "$oid": "6895d4859af344ccf9c75d4c"
  },
  "Aname": {
    "Name": "PRINCESS",
    "Mname": "",
    "Surname": "OBIEKE"
  },
  "State": "",
  "LocalGovernment": "",
  "Sex": "",
  "Bloodgroup": "",
  "PhoneNumber": "",
  "EmergencyNo": "",
  "RegNo": "J25/124",
  "Validity": "2025-2027",
  "picturepath": "image/49892.jpg",
  "imgurl": "https://drive.google.com/file/d/18BTRMJFWgXXOysciwpedGlsvPCzopj_D/view?usp=drivesdk",
  "image": "https://lh3.googleusercontent.com/d/18BTRMJFWgXXOysciwpedGlsvPCzopj_D=s400?authuser=0",
  "time": "2025-08-08 10:42:13",
  "field": "89da0b6d-4cc5-41a7-b1f2-74e13f7d450b",
  "id": 502,
  "__v": 0
},
{
  "_id": {
    "$oid": "6895d4be9af344ccf9c75d53"
  },
  "Aname": {
    "Name": "MORIAN",
    "Mname": "",
    "Surname": "AKANDU"
  },
  "State": "",
  "LocalGovernment": "",
  "Sex": "F",
  "Bloodgroup": "",
  "PhoneNumber": "",
  "EmergencyNo": "",
  "RegNo": "M24/003",
  "Validity": "2025-2027",
  "picturepath": "image/80869.jpg",
  "imgurl": "https://drive.google.com/file/d/1XUAcAos56vdk-fgVy_v_C_fXF9FlVW2h/view?usp=drivesdk",
  "image": "https://lh3.googleusercontent.com/d/1XUAcAos56vdk-fgVy_v_C_fXF9FlVW2h=s400?authuser=0",
  "time": "2025-08-08 10:43:10",
  "field": "9b5d9240-ac6f-4eda-9843-d692a6b38718",
  "id": 503,
  "__v": 0
},
{
  "_id": {
    "$oid": "6895d50e9af344ccf9c75d5a"
  },
  "Aname": {
    "Name": "CHIAMAKA",
    "Mname": "ANASTASIA",
    "Surname": "ONONIWU"
  },
  "State": "",
  "LocalGovernment": "",
  "Sex": "",
  "Bloodgroup": "",
  "PhoneNumber": "",
  "EmergencyNo": "",
  "RegNo": "S24/098",
  "Validity": "2024-2026",
  "picturepath": "image/14268.jpg",
  "imgurl": "https://drive.google.com/file/d/1WqU5M6zUshmdXmGLShuLGhxMWU57pJzU/view?usp=drivesdk",
  "image": "https://lh3.googleusercontent.com/d/1WqU5M6zUshmdXmGLShuLGhxMWU57pJzU=s400?authuser=0",
  "time": "2025-08-08 10:44:30",
  "field": "bd36f17e-79d2-4baf-8dd5-c10c45793b48",
  "id": 504,
  "__v": 0
},
{
  "_id": {
    "$oid": "6895d5649af344ccf9c75d61"
  },
  "Aname": {
    "Name": "JENNIFER",
    "Mname": "",
    "Surname": "CHUKWU"
  },
  "State": "",
  "LocalGovernment": "",
  "Sex": "U",
  "Bloodgroup": "",
  "PhoneNumber": "",
  "EmergencyNo": "",
  "RegNo": "J25/036",
  "Validity": "2025-2027",
  "picturepath": "image/25818.jpg",
  "imgurl": "https://drive.google.com/file/d/11dWcivasBnt_6IIRHjJEAnq4eMdTVpRP/view?usp=drivesdk",
  "image": "https://lh3.googleusercontent.com/d/11dWcivasBnt_6IIRHjJEAnq4eMdTVpRP=s400?authuser=0",
  "time": "2025-08-08 10:45:56",
  "field": "84d07d8d-a92b-4300-932f-91194bdacb7e",
  "id": 505,
  "__v": 0
},
{
  "_id": {
    "$oid": "6895d5a19af344ccf9c75d68"
  },
  "Aname": {
    "Name": "DIVINE",
    "Mname": "",
    "Surname": "ODINAKA"
  },
  "State": "IMO",
  "LocalGovernment": "",
  "Sex": "S24/085",
  "Bloodgroup": "",
  "EmergencyNo": "",
  "RegNo": "S24/085",
  "Validity": "2024-2026",
  "picturepath": "image/16040.jpg",
  "imgurl": "https://drive.google.com/file/d/1LxLO9Vk9W6ZJW6OrsJu12S0uddXim_f3/view?usp=drivesdk",
  "image": "https://lh3.googleusercontent.com/d/1LxLO9Vk9W6ZJW6OrsJu12S0uddXim_f3=s400?authuser=0",
  "time": "2025-08-08 10:46:57",
  "field": "3cdba8ec-4b1c-45c6-95b8-c9d6454f74d7",
  "id": 506,
  "__v": 0,
  "Gender": "S24/085",
  "PhoneNumber": ""
},
{
  "_id": {
    "$oid": "6895d5dc9af344ccf9c75d6f"
  },
  "Aname": {
    "Name": "FAITH",
    "Mname": "",
    "Surname": "NNACHETA"
  },
  "State": "",
  "LocalGovernment": "",
  "Sex": "",
  "Bloodgroup": "",
  "PhoneNumber": "",
  "EmergencyNo": "",
  "RegNo": "S24/070",
  "Validity": "2024-2026",
  "picturepath": "image/12088.jpg",
  "imgurl": "https://drive.google.com/file/d/10WuGr5IJFXImi9T4sG4asRBt4tgZPAKO/view?usp=drivesdk",
  "image": "https://lh3.googleusercontent.com/d/10WuGr5IJFXImi9T4sG4asRBt4tgZPAKO=s400?authuser=0",
  "time": "2025-08-08 10:47:56",
  "field": "8caa98a4-4339-4f0f-ba61-0261b2f70f78",
  "id": 507,
  "__v": 0
},
{
  "_id": {
    "$oid": "6895d60a9af344ccf9c75d76"
  },
  "Aname": {
    "Name": "CHIDINMA",
    "Mname": "",
    "Surname": "IHECHI"
  },
  "State": "",
  "LocalGovernment": "",
  "Sex": "",
  "Bloodgroup": "",
  "PhoneNumber": "",
  "EmergencyNo": "",
  "RegNo": "M24/048",
  "Validity": "2024-2026",
  "picturepath": "image/30002.jpg",
  "imgurl": "https://drive.google.com/file/d/1CTazT8oFnJi_CrGZCuKdpU8M31GAdJm5/view?usp=drivesdk",
  "image": "https://lh3.googleusercontent.com/d/1CTazT8oFnJi_CrGZCuKdpU8M31GAdJm5=s400?authuser=0",
  "time": "2025-08-08 10:48:42",
  "field": "9f666e91-22c0-4278-8c90-a0c5f0cb66fa",
  "id": 508,
  "__v": 0
},
{
  "_id": {
    "$oid": "6895d6439af344ccf9c75d7d"
  },
  "Aname": {
    "Name": "SUCCESS",
    "Mname": "",
    "Surname": "OKOSOWEI"
  },
  "State": "",
  "LocalGovernment": "",
  "Sex": "",
  "Bloodgroup": "",
  "PhoneNumber": "",
  "EmergencyNo": "",
  "RegNo": "M24/095",
  "Validity": "2024-2026",
  "picturepath": "image/04535.jpg",
  "imgurl": "https://drive.google.com/file/d/1DtbgFrltwg4rhNUYoUxEy5k-ZUHVF7BE/view?usp=drivesdk",
  "image": "https://lh3.googleusercontent.com/d/1DtbgFrltwg4rhNUYoUxEy5k-ZUHVF7BE=s400?authuser=0",
  "time": "2025-08-08 10:49:39",
  "field": "c456417b-cd45-4bdb-bc3f-c697bf25d29a",
  "id": 509,
  "__v": 0
},
{
  "_id": {
    "$oid": "6895d67b9af344ccf9c75d84"
  },
  "Aname": {
    "Name": "CHINAGOROM",
    "Mname": "",
    "Surname": "NWOKEDI"
  },
  "State": "",
  "LocalGovernment": "",
  "Sex": "",
  "Bloodgroup": "",
  "PhoneNumber": "",
  "EmergencyNo": "",
  "RegNo": "M24/073",
  "Validity": "2024-2026",
  "picturepath": "image/85521.jpg",
  "imgurl": "https://drive.google.com/file/d/1wrIHOpwq0XkhhCSolGnW48ekGoFhN63O/view?usp=drivesdk",
  "image": "https://lh3.googleusercontent.com/d/1wrIHOpwq0XkhhCSolGnW48ekGoFhN63O=s400?authuser=0",
  "time": "2025-08-08 10:50:35",
  "field": "8148444f-240d-4936-b48c-58378c88fd7b",
  "id": 510,
  "__v": 0
},
{
  "_id": {
    "$oid": "6895d6b89af344ccf9c75d8b"
  },
  "Aname": {
    "Name": "VIVIAN",
    "Mname": "NMESOMACHI",
    "Surname": "DURU"
  },
  "State": "",
  "LocalGovernment": "",
  "Sex": "",
  "Bloodgroup": "",
  "PhoneNumber": "",
  "EmergencyNo": "",
  "RegNo": "M24/026",
  "Validity": "2024-2026",
  "picturepath": "image/65411.jpg",
  "imgurl": "https://drive.google.com/file/d/1oKhNMnnkefsDEe14RS3F8wC_zwOhPyVS/view?usp=drivesdk",
  "image": "https://lh3.googleusercontent.com/d/1oKhNMnnkefsDEe14RS3F8wC_zwOhPyVS=s400?authuser=0",
  "time": "2025-08-08 10:51:36",
  "field": "c7e5c381-2d06-4a13-9339-e3b348cee301",
  "id": 511,
  "__v": 0
},
{
  "_id": {
    "$oid": "6895d6fd9af344ccf9c75d92"
  },
  "Aname": {
    "Name": "FAVPUR",
    "Mname": "",
    "Surname": "EZEANYANASOM"
  },
  "State": "",
  "LocalGovernment": "",
  "Sex": "FEMALE",
  "Bloodgroup": "",
  "PhoneNumber": "",
  "EmergencyNo": "",
  "RegNo": "M24/031",
  "Validity": "2024-2026",
  "picturepath": "image/44669.jpg",
  "imgurl": "https://drive.google.com/file/d/165uEO_S1p2-fghUCSh0WskFnXQV5U5Hr/view?usp=drivesdk",
  "image": "https://lh3.googleusercontent.com/d/165uEO_S1p2-fghUCSh0WskFnXQV5U5Hr=s400?authuser=0",
  "time": "2025-08-08 10:52:45",
  "field": "5a51e6c4-f8a3-4c30-bece-73362d4a88d1",
  "id": 512,
  "__v": 0
},
{
  "_id": {
    "$oid": "6895d7409af344ccf9c75d99"
  },
  "Aname": {
    "Name": "DABERECHI",
    "Mname": "DEBORAH",
    "Surname": "UBAOZOR"
  },
  "State": "",
  "LocalGovernment": "",
  "Sex": "",
  "Bloodgroup": "",
  "PhoneNumber": "",
  "EmergencyNo": "",
  "RegNo": "J24/125",
  "Validity": "2024-2026",
  "picturepath": "image/10658.jpg",
  "imgurl": "https://drive.google.com/file/d/1Ss7niAQeS68WkJgZl5MgKARmvocnKNa6/view?usp=drivesdk",
  "image": "https://lh3.googleusercontent.com/d/1Ss7niAQeS68WkJgZl5MgKARmvocnKNa6=s400?authuser=0",
  "time": "2025-08-08 10:53:52",
  "field": "7937f70b-9e7f-4d3d-ba47-fe62302f7099",
  "id": 513,
  "__v": 0
}
]
